[
{"title": "天净沙·秋", "author": "白朴", "paragraphs": "孤村落日残霞，轻烟老树寒鸦，一点飞鸿影下。青山绿水，白草红叶黄花。", "topic": "秋天", "notes": ["天净沙：曲牌名。", "秋：题目。", "残霞：快消散的晚霞。", "寒鸦：天寒即将归林的乌鸦。", "飞鸿：天空中的鸿雁。", "飞鸿影下：雁影掠过。", "白草：枯萎而不凋谢的白草。", "黄花：菊花。", "红叶：枫叶。"], "background": "白朴《天净沙》共四首，这是第三首，主要写秋景。是作者于宋亡后寓居金陵（今南京）时所作，具体创作年代不详。"},
{"title": "渔家傲·秋思", "author": "范仲淹", "paragraphs": "塞下秋来风景异，衡阳雁去无留意。四面边声连角起，千嶂里，长烟落日孤城闭。\t浊酒一杯家万里，燕然未勒归无计。羌管悠悠霜满地，人不寐，将军白发征夫泪。", "topic": "秋天", "notes": ["渔家傲：又名《吴门柳》、《忍辱仙人》、《荆溪咏》、《游仙关》。", "塞：边界要塞之地，这里指西北边疆。", "衡阳雁去：传说秋天北雁南飞，至湖南衡阳回雁峰而止，不再南飞。", "边声：边塞特有的声音，如大风、号角、羌笛、马啸的声音。", "千嶂：绵延而峻峭的山峰；崇山峻岭。", "燕然未勒：指战事未平，功名未立。", "燕然：即燕然山，今名杭爱山，在今蒙古国境内。据《后汉书·窦宪传》记载，东汉窦宪率兵追击匈奴单于，去塞三千余里，登燕然山，刻石勒功而还。", "羌管：即羌笛，出自古代西部羌族的一种乐器。", "悠悠：形容声音飘忽不定。", "寐：睡，不寐就是睡不着。"], "background": "宋康定元年（1040年）至庆历三年（1043年）间，范仲淹任陕西经略副使兼延州知州。宋仁宗年间，范仲淹被朝廷派往西北前线，承担起北宋西北边疆防卫重任。这首词作于北宋与西夏战争对峙时期。"},
{"title": "天净沙·秋思", "author": "马致远", "paragraphs": "枯藤老树昏鸦，小桥流水人家，古道西风瘦马。夕阳西下，断肠人在天涯。", "topic": "秋天", "notes": ["天净沙：曲牌名，属越调。又名“塞上秋”。", "枯藤：枯萎的枝蔓。昏鸦：黄昏时归巢的乌鸦。昏：傍晚。", "人家：农家。此句写出了诗人对温馨的家庭的渴望。", "古道：已经废弃不堪再用的古老驿道（路）或年代久远的驿道。西风：寒冷、萧瑟的秋风。瘦马：瘦骨如柴的马。", "断肠人：形容伤心悲痛到极点的人，此指漂泊天涯、极度忧伤的旅人。", "天涯：远离家乡的地方。"], "background": "马致远年轻时热衷功名，但由于元朝统治者实行民族高压政策，因而一直未能得志。他几乎一生都在过着漂泊无定的生活。他也因此而郁郁不得志，困窘潦倒一生。于是在羁旅途中，写下了这首《天净沙·秋思》。"},
{"title": "诉衷情近·雨晴气爽", "author": "柳永", "paragraphs": "雨晴气爽，伫立江楼望处。澄明远水生光，重叠暮山耸翠。遥认断桥幽径，隐隐渔村，向晚孤烟起。\t残阳里。脉脉朱阑静倚。黯然情绪，未饮先如醉。愁无际。暮云过了，秋光老尽，故人千里。竟日空凝睇。", "topic": "秋天", "notes": ["诉衷情近：词牌名，《乐章集》注“林钟商”。双调七十五字，上片七句三仄韵，下片九句六仄韵。", "雨晴气爽：雨过天晴，秋高气爽。爽：清爽的意思。", "伫立：长时间地站立。", "澄明：清澈明净。生光：发出光辉。", "耸翠：形容山峦、树木等高耸苍翠。", "遥认：从远处辨认。断桥：桥名。在今浙江省杭州市孤山旁，以孤山之路至此而断，故名。此处不一定特指西湖的断桥。幽径：僻静的小路。", "隐隐：指隐约；不分明。", "向晚：临近晚上。孤烟：远处独起的炊烟。", "脉脉：默默地用眼神或行动表达情意的样子。朱阑：同“朱栏”，朱红色的围栏。", "黯然：情绪低落、心情沮丧的样子。", "无际：犹无边；无涯。", "老尽：衰竭。", "竟日：犹终日，整天。凝睇：凝视；注视；目不斜视。”"], "background": "柳永在北宋景祐元年（1034）考中进士之前的数年间，曾经像断梗浮萍一样漫游江南。他的足迹曾到过江、浙、楚、淮等地，依旧羁旅落魄，“奉旨填词”。这首《诉衷情近》就是其漫游江南水乡时所作的一首思念京都故人的词作。"},
{"title": "临江仙引·渡口", "author": "柳永", "paragraphs": "渡口、向晚，乘瘦马、陟平冈。西郊又送秋光。对暮山横翠，衫残叶飘黄。凭高念远，素景楚天，无处不凄凉。\t香闺别来无信息，云愁雨恨难忘。指帝城归路，但烟水茫茫。凝情望断泪眼，尽日独立斜阳。", "topic": "秋天", "notes": ["临江仙引：词牌名，正体双调七十四字，前段十句，四平韵；后段六句，三平韵。", "向晚：近晚，傍晚。", "陟（zhì）：登上。平冈：平缓的山脊。", "暮山：暮色中的山。横翠：翠色横亘。", "衬：以暮山为背景衬托。飘黄：黄叶飘零。", "素景：秋景。楚天：长江中南部天空，此指南方天色。", "云愁雨恨：因男女恋情而引起的烦恼。", "帝城：京城。", "凝情：全神贯注。望断泪眼：即泪眼望断。望断，望尽。"], "background": "柳永屡次下第，经过艰难曲折，终于在宋仁宗景祐元年（1034年）考中进士，随即踏入仕途。这时词人约近五十岁了。他入仕之后长期担任地方州郡的掾吏、判官等职，久困选调，辗转宦游各地，很不得志。这首《临江仙引》就是他入仕之后所写的羁旅行役之词。"},
{"title": "少年游·长安古道马迟迟", "author": "柳永", "paragraphs": "长安古道马迟迟，高柳乱蝉嘶。夕阳鸟外，秋风原上，目断四天垂。\t归云一去无踪迹，何处是前期？狎兴生疏，酒徒萧索，不似少年时。", "topic": "秋天", "notes": ["马迟迟：马行缓慢的样子。", "乱蝉嘶：一作“乱蝉栖”。", "鸟：又作“岛”，指河流中的洲岛。", "原上：乐游原上，在长安西南。", "目断：极目望到尽头。四天垂：天的四周夜幕降临。", "归云：飘逝的云彩。这里比喻往昔经历而现在不可复返的一切。此句一作“归去一云无踪迹”。", "前期：以前的期约。既可指往日的志愿心期又可指旧日的欢乐约期。", "狎兴：游乐的兴致。狎：亲昵而轻佻。", "酒徒：酒友。萧索：零散，稀少，冷落，寂寞。", "少年时：又作“去年时”。"], "background": ""},
{"title": "浪淘沙·一叶忽惊秋", "author": "贺铸", "paragraphs": "一叶忽惊秋。分付东流。殷勤为过白苹洲。洲上小楼帘半卷，应认归舟。\t回首恋朋游。迹去心留。歌尘萧散梦云收。惟有尊前曾见月，相伴人愁。", "topic": "秋天", "notes": ["分付：意为交给。", "白苹洲：泛指长满白色苹花的沙洲。", "歌尘：形容歌声动听。", "梦云：战国宋玉《高唐赋》中的人物，所以泛指美女。"], "background": ""},
{"title": "河渎神", "author": "张泌", "paragraphs": "古树噪寒鸦，满庭枫叶芦花。昼灯当午隔轻纱，画阁珠帘影斜。\t门外往来祈赛客，翩翩帆落天涯。回首隔江烟火，渡头三两人家。", "topic": "秋天", "notes": ["河渎神：唐教坊曲名，双调四十九字，上片四句四平韵，下片四句四仄韵。", "寒鸦：秋冬时节的乌鸦。", "“昼灯”一句：昼灯：祠庙中的长明灯。轻纱：指灯罩。画阁：画阁：彩绘的楼阁，指祠庙。斜：斜着的灯影。 [2]  ", "祈赛：即祈报，祭祀名。春祈丰年，秋报神功。又遇水旱则祈，既如愿而报。祈赛客，祈报的百姓。翩翩：往来的样子。", "烟火：百姓做饭时的炊烟袅袅。渡头：渡津。三两人家。"], "background": "这首词创作具体时间不详。作者乘船经过河神庙内外，恰巧遇到祠庙祈赛，行客过往匆匆，暮霭沉沉，隔岸遥观，只能隐约见到星星点点的人家烟火散落江上。词人内心倍感孤独和凄凉，于是写下这首词，表达词人深浓的客途秋恨。"},
{"title": "玉楼春·别后不知君远近", "author": "欧阳修", "paragraphs": "别后不知君远近，触目凄凉多少闷。渐行渐远渐无书，水阔鱼沉何处问。\t夜深风竹敲秋韵，万叶千声皆是恨。故攲单枕梦中寻，梦又不成灯又烬。", "topic": "秋天", "notes": ["玉楼春：词牌名。《词谱》谓五代后蜀顾夐词起句有“月照玉楼春漏促”“柳映玉楼春欲晚”句；", "起句有“日照玉楼花似锦”“春早玉楼烟雨夜”句，因取以调名。亦称“木兰花”“春晓曲”“西湖曲”“惜春容”“归朝欢令”等。双调五十六字，前后阕格式相同，各三仄韵，一韵到底。", "多少：不称多少之意。", "书：书信。", "鱼沉：鱼不传书。古代有鱼雁传书的传说，这里指音讯全无。", "秋韵：即秋声。此谓风吹竹声。", "攲（yǐ）：古通“倚”，斜，倾。单枕：孤枕。", "烬（jìn）：灯芯烧尽成灰。"], "background": "本首词的具体创作时间不详。这首写别后相思愁绪之词，当为欧阳修早期所作，是以代言体（即女性第一人称方式）形式表达闺中思妇离情别绪的作品。"},
{"title": "荷叶杯·镜水夜来秋月", "author": "温庭筠", "paragraphs": "镜水夜来秋月，如雪。采莲时，小娘红粉对寒浪。惆怅，正思惟。", "topic": "秋天", "notes": ["镜水：平静明净的水。唐李肇《唐国史补》卷下：“凡造物南水土，故江东官纱绫、官纸者，镜水之故也。”", "小娘：此指采莲的少女。红粉：女子化妆所用的胭脂和铅粉，这里指妆扮得十分美丽的少女面庞。寒浪：寒凉的水波。", "思惟：思量，思念。《汉书·张汤传》：“使专精神，忧念天下，思惟得失。”"], "background": "清晨，采莲时候，采莲少女红润的粉面，影照在清冷明彻的镜水之上，词人有感而作。"},
{"title": "浣溪沙·败叶填溪水已冰", "author": "纳兰性德", "paragraphs": "败叶填溪水已冰，夕阳犹照短长亭。何年废寺失题名。\t倚马客临碑上字，斗鸡人拨佛前灯，净消尘土礼金经。", "topic": "秋天", "notes": ["浣溪沙：唐教坊曲名，因春秋时期人西施浣纱于若耶溪而得名，后用作词牌名，又名“浣溪纱”“小庭花”等。此调有平仄两体。全词分上下两片，上片三句全用韵，下片末二句用韵，过片二句用对偶句的居多。音节明快，句式整齐，易于上口，为婉约派与豪放派多数词人所常用。", "败叶：干枯凋落的树叶。", "题名：寺名。", "斗鸡人：斗鸡本为一种游戏，战国时即已存在。此处“斗鸡人”与前“倚马客”对举，谓到此寺中之人已非往日的善男信女，而是前来闲游的过客，或是贵族豪门的公子哥们。", "金经：佛经，即《金刚经》，为《金刚般若经》或《金刚般若波罗蜜经》之简称。自东晋以后有多种译本。"], "background": "康熙年间，词人随从康熙皇帝出巡时见到了“废寺”，由此生情动感，遂填词以寄今昔之慨。"},
{"title": "苏幕遮·怀旧", "author": "范仲淹", "paragraphs": "碧云天，黄叶地，秋色连波，波上寒烟翠。山映斜阳天接水，芳草无情，更在斜阳外。\t黯乡魂，追旅思，夜夜除非，好梦留人睡。明月楼高休独倚，酒入愁肠，化作相思泪。", "topic": "秋天", "notes": ["苏幕遮：原唐教坊曲名，来自西域，后用作词牌名。又名“云雾敛”“鬓云松令”。双调，六十二字，上下片各五句。", "“波上”句：江波之上笼罩着一层翠色的寒烟。烟本呈白色，因其上连碧天，下接绿波，远望即与碧天同色，正所谓“秋水共长天一色”。", "“芳草”二句：意思是，草地绵延到天涯，似乎比斜阳更遥远。“芳草”常暗指故乡，因此，这两句有感叹故乡遥远之意。", "黯乡魂：因思念家乡而黯然伤神。黯，形容心情忧郁。乡魂，即思乡的情思。语出", " 《别赋》：“黯然销魂者，唯别而已矣。\"", "追旅思（sī）：撇不开羁旅的愁思。追，追随，这里有缠住不放的意思。旅思，旅居在外的愁思。思，心绪，情怀。"], "background": "这首词作于公元1040年（宋仁宗康定元年）至公元1043年（庆历三年）间，当时范仲淹正在西北边塞的军中任陕西四路宣抚使，主持防御西夏的军事。"},
{"title": "风流子·秋郊即事", "author": "纳兰性德", "paragraphs": "平原草枯矣，重阳后、黄叶树骚骚。记玉勒青丝，落花时节，曾逢拾翠，忽听吹箫。今来是、烧痕残碧尽，霜影乱红凋。秋水映空，寒烟如织，皂雕飞处，天惨云高。\t人生须行乐，君知否？容易两鬓萧萧。自与东君作别，刬地无聊。算功名何许，此身博得，短衣射虎，沽酒西郊。便向夕阳影里，倚马挥毫。", "topic": "秋天", "notes": ["骚骚：秋日风吹草木声。", "玉勒（lè）青丝：玉饰之马衔及马缰绳。此代指骑马游春。", "拾翠：拾取翠鸟羽毛作首饰。后多代指女子或女子游春踏青。", "寒烟如织：清寒浓郁的烟雾弥漫在四处。", "皂（zào）雕（diāo）：一种黑色的大型猛禽。", "天惨（cǎn）：天色昏暗不明。", "东君：司春之神。", "刬（chǎn）地：只是、依旧、照旧。", "短衣射虎：短衣，打猎的装束。射虎，用汉李广故事。《史记·李将军列传》：“广所居郡，闻有虎，尝自射之。及居右北平，射虎，虎腾伤广，广亦竟射杀之。”后在诗词中常以此形容英雄气概、英勇豪迈。"], "background": "这首词属于纳兰性德早期的作品。纳兰性德夙怀经邦济世的抱负，但难以实现，因而常自慨叹。这首词便是纳兰与友人一起出行想起自己的际遇因而写下这首词。"},
{"title": "关河令·秋阴时晴渐向暝", "author": "周邦彦", "paragraphs": "秋阴时晴渐向暝，变一庭凄冷。伫听寒声，云深无雁影。\t更深人去寂静，但照壁孤灯相映。酒已都醒，如何消夜永！", "topic": "秋天", "notes": ["《片玉词》“关河令”下注：“《清真集》不载，时刻‘清商怨’。”清商怨，源于古乐府，曲调哀婉。", "曾以此曲填写思乡之作，首句是“关河愁思望处满”。", "遂取“关河”二字，命名为“关河令”，隐寓着羁旅思家之意。自此，调名、乐曲跟曲词切合一致了。", "时：片时、偶尔的意思。晴：一作“作”。", "伫听：久久地站着倾听。伫，久立而等待。寒声：即秋声，指秋天的风声、雨声、虫鸟哀鸣声等。此处是指雁的鸣叫声。", "照壁：古时筑于寺庙、广宅前的墙屏。与正门相对，作遮蔽、装饰之用，多饰有图案、文字。亦谓影壁，指大门内或屏门内做屏蔽的墙壁。也有木制的，下有底座，可以移动，又称照壁、照墙。", "消夜永：度过漫漫长夜。夜永，犹言长夜。"], "background": ""},
{"title": "甘草子·秋暮", "author": "柳永", "paragraphs": "秋暮。乱洒衰荷，颗颗真珠雨。雨过月华生，冷彻鸳鸯浦。\t池上凭阑愁无侣。奈此个、单栖情绪。却傍金笼共鹦鹉。念粉郎言语。", "topic": "秋天", "notes": ["甘草子：词牌名。《乐章集》注“正宫”。格一：双调，四十七字。前段五句，四仄韵；后段四句，四仄韵。", "暮：傍晚 将近", "衰：衰落，衰败。衰荷：将败的荷花。", "真浦雨：像珍浦样的雨浦。", "月华：月光，月光照射到云层上，呈现在月亮周围的彩栖光环。生：产生、出现。", "彻：程度极深，透的意思。鸳鸯浦：地名，水池边。这里是虚写。浦：水边或河流入海的地方。如浦口等。此指水塘。鸳鸯浦：鸳鸯栖息的水滨。比喻美栖荟萃之所。", "凭阑：靠着栏杆，“阑”通“栏”。", "奈：奈何，怎么办。", "单栖：孤寂的停留。独宿。情绪：情感。", "却：表示转折。傍：靠近。共：在一起。", "念：道白，说。粉郎：", "，三国魏玄学家。字平叔。南阳宛县(今河南南阳)人。汉大将军何进之孙。", "纳晏母为妾，晏被收养，为操所宠爱。少以才秀知名，好老、庄言，“美姿仪而绝白”，喜敷粉，“行步顾影”，人称“傅粉何郎”。在这里指所思之人。"], "background": ""},
{"title": "朝天子·秋夜吟", "author": "李致远", "paragraphs": "梵宫、晚钟。落日蝉声送。半规凉月半帘风，骚客情尤重。何处楼台，笛声悲动？二毛斑秋夜永。楚峰，几重？遮不断相思梦。", "topic": "秋天", "notes": ["梵宫：即佛寺。", "半规：圆形为规，半规即半圆。", "二毛：鬓发斑白。", "楚峰：指四川、湖北两省边境的巫山一带，有十二峰，其中神女峰最奇。"], "background": ""},
{"title": "齐天乐·竹深不放斜阳度", "author": "吴文英", "paragraphs": "竹深不放斜阳度，横披澹墨林沼。断莽平烟，残莎剩水，宜得秋深才好。荒亭旋扫。正著酒寒轻，弄花春小。障锦西风，半围歌袖半吟草。\t独游清兴易懒，景饶人未胜，乐事长少。柳下交车，尊前岸帻，同抚云根一笑。秋香未老。渐风雨西城，暗欹客帽。背月移舟，乱鸦溪树晓。", "topic": "秋天", "notes": "", "background": ""},
{"title": "生查子·秋社", "author": "吴文英", "paragraphs": "当楼月半奁，曾买菱花处。愁影背阑干，素发残风露。\t神前鸡酒盟，歌断秋香户。泥落画梁空，梦想青春语。", "topic": "秋天", "notes": "", "background": ""},
{"title": "点绛唇·高柳蝉嘶", "author": "汪藻", "paragraphs": "高柳蝉嘶，采菱歌断秋风起。晚云如髻。湖上山横翠。\t帘卷西楼，过雨凉生袂。天如水。画楼十二。有个人同倚。", "topic": "秋天", "notes": "", "background": ""},
{"title": "河传·秋光满目", "author": "徐昌图", "paragraphs": "秋光满目。风清露白，莲红水绿。何处梦回？弄珠拾翠盈盈，倚兰桡，眉黛蹙。\t采莲调稳，吴侣声相续，倚棹吴江曲。鹭起暮天，几双交颈鸳鸯，入芦花，深处宿。", "topic": "秋天", "notes": ["弄珠拾翠：语出曹植《洛神赋》：“或采明珠，或拾翠羽。”拾翠：拾取翠鸟羽毛以为首饰。后以指妇女嬉游的景象。", "采莲调：采莲子，词调名。"], "background": ""},
{"title": "醉公子·漠漠秋云澹", "author": "顾夐", "paragraphs": "漠漠秋云澹，红藕香侵槛。枕倚小山屏，金铺向晚扃。\t睡起横波慢，独望情何限！衰柳数声蝉，魂销似去年。", "topic": "秋天", "notes": ["澹：“淡”的异体字。浅、薄之意。", "槛：窗户下或长廓旁的栏杆。", "金铺：门上之铺首。作龙蛇诸兽之形，用以衔环。扃：门窗箱柜上的插关。这里是关门之意。"], "background": ""},
{"title": "点绛唇·县斋愁坐作", "author": "葛胜仲", "paragraphs": "秋晚寒斋，藜床香篆横轻雾。闲愁几许。梦逐芭蕉雨。\t云外哀鸿，似替幽人语。归不去。乱山无数。斜日荒城鼓。", "topic": "秋天", "notes": "", "background": ""},
{"title": "更漏子·对秋深", "author": "孙光宪", "paragraphs": "对秋深，离恨苦，数夜满庭风雨。凝想坐，敛愁眉，孤心似有违。\t红窗静，画帘垂，魂消地角天涯。和泪听，断肠窥，漏移灯暗时。", "topic": "秋天", "notes": ["孤心：负心。", "漏：古代计时工具。"], "background": ""},
{"title": "卜算子·秋晚集杜句吊贾傅", "author": "杨冠卿", "paragraphs": "苍生喘未苏，贾笔论孤愤。文采风流今尚存，毫发无遗恨。\t凄恻近长沙，地僻秋将尽。长使英雄泪满襟，天意高难问。", "topic": "秋天", "notes": "", "background": ""},
{"title": "更漏子·秋", "author": "张淑芳", "paragraphs": "墨痕香，红蜡泪。点点愁人离思。桐叶落，蓼花残。雁声天外寒。\t五云岭，九溪坞。待到秋来更苦。风淅淅，水淙淙。不教蓬径通。", "topic": "秋天", "notes": "", "background": ""},
{"title": "浪淘沙·秋", "author": "朱栴", "paragraphs": "塞下景荒凉，淡薄秋光，金风淅淅透衣裳。读罢安仁《秋兴赋》，憀栗悲伤。\t廿载住边疆，两鬓成霜，天边鸿雁又南翔。借问夏城屯戍客，是否思乡？", "topic": "秋天", "notes": ["这首词选自《宣德宁夏志》，《嘉靖宁夏新志》、《弘治宁夏新志》、《万历朔方新志》、《朔方道志》亦收录此词，题目作《浪淘沙·塞垣秋思》。浪淘沙，词牌名。", "安仁《秋兴赋》：指西晋文学家潘岳，字安仁，工诗赋，曾作《秋兴赋》。", "憀栗：同“寥栗”，凄怆貌。", "夏城：即今宁夏回族自治区首府银川市老城。宋为西夏都城，明为九边重镇宁夏镇城，故称镇城为夏城。屯戍客：驻守边疆的人。"], "background": ""},
{"title": "浣溪沙·月底栖鸦当叶看", "author": "王国维", "paragraphs": "月底栖鸦当叶看。推窗跕跕堕枝间。霜高风定独凭栏。\t觅句心肝终复在，掩书涕泪苦无端。可怜衣带为谁宽。", "topic": "秋天", "notes": ["鸦：有些版本作“雅”字。", "跕跕(dié)：下堕貌。《后汉书·", "传》：“仰视飞鸢，跕跕堕水中。“", "风定：风停止。", "觅句心肝：苦寻诗句。", "无端：无缘无故。", "可怜衣带为谁宽：引", "《凤栖梧》词“衣带渐宽终不悔，为伊消得人憔悴”。"], "background": "这首词是王国维于1905年在固原所作。当时王国维远离家人，独自一人在外地任教，借此词抒发自己内心的孤独。"},
{"title": "齐天乐·夜来疏雨鸣金井", "author": "王月山", "paragraphs": "夜来疏雨鸣金井，一叶舞空红浅。莲渚收香，兰皋浮爽，凉思顿欺班扇。秋光苒苒。任老却芦花，西风不管。清兴难磨，几回有句到诗卷。\t长安故人别後，料征鸿声里，画阑凭偏。横竹吹商，疏砧点月，好梦又随云远。间愁似线。甚击损柔肠，不堪裁翦。听著鸣蛩，一声声是怨。", "topic": "秋天", "notes": ["渚：水中小洲，水边。　莲渚：水边莲花。", "兰皋：有兰草之岸。", "冉冉：行貌，渐进之意。", "横竹：管乐器笛。　商：五音之一。", "砧：捣衣石。"], "background": ""},
{"title": "青杏儿·秋", "author": "朱栴", "paragraphs": "午枕梦初残，高楼上，独凭阑干。清商应律金风至，砧声断续，笳音幽怨，雁阵惊寒。\t景物不堪看，凝眸处愁有千般。秋光谈薄人情似，迢迢野水，茫茫衰草，隐隐青山。", "topic": "秋天", "notes": ["这首词选自《宣德宁夏志》。青杏儿，词牌名。", "独凭阑干：《宁夏志笺证》（吴忠礼笺证）作“儿凭阑干”，误。", "清商：古五音之一，商声。应律：应和乐律。金风：秋风。", "砧声断续：意思是时不时传来捣衣声。砧，捣衣石。", "雁阵：群雁飞行的行列整齐，好像军队布阵一样。", "凝眸：眼神集中不流动；注视。", "迢迢：遥远貌。"], "background": ""},
{"title": "齐天乐·秋声馆赋秋声", "author": "厉鹗", "paragraphs": "簟凄灯暗眠还起，清商几处催发？碎竹虚廊，枯莲浅渚，不辨声来何叶？桐飙又接。尽吹入潘郎，一簪愁发。已是难听，中宵无用怨离别。\t阴虫还更切切。玉窗挑锦倦，惊响檐铁。漏断高城，钟疏野寺，遥送凉潮呜咽。微吟渐怯。讶篱豆花开，雨筛时节。独自开门，满庭都是月。", "topic": "秋天", "notes": ["清商：原为古五音之一。此处指秋风。", "飙：泛指风。", "潘郎：指晋潘岳。", "檐铁：檐马。亦谓之风铃，风马儿。悬于檐下，风起则铮有声。"], "background": ""},
{"title": "秋蕊香·池苑清阴欲就", "author": "晏几道", "paragraphs": "池苑清阴欲就。还傍送春时候。眼中人去难欢偶。谁共一杯芳酒。\t朱阑碧砌皆如旧。记携手。有情不管别离久。情在相逢终有。", "topic": "秋天", "notes": ["池苑句：言树已成荫，时已春暮。就，成。", "还傍句：言春将归去。还，已经。傍，临近。", "难欢偶：一本作“欢难偶”，犹言难以再有往日的欢乐。偶，遇。", "朱阑碧砌：朱红的阑干，青碧的台阶。李煜《虞美人》词：“雕阑玉砌应犹在，只是朱颜改。”晏词由此化出。"], "background": ""},
{"title": "好事近·夜起倚危楼", "author": "王国维", "paragraphs": "夜起倚危楼，楼角玉绳低亚。惟有月明霜冷，浸万家鸳瓦。\t人间何苦又悲秋，正是伤春罢。却向春风亭畔，数梧桐叶下。", "topic": "秋天", "notes": ["好事近：词牌名，又名《钓船笛》，《张子野词》。", "危楼：危即高的意思，指高楼。", "楼角：高楼的檐角。玉绳：星名，《春秋元命苞》：玉衡北两星为玉绳。亚：通“压”，低垂貌。", "惟有：只有。", "鸳瓦：鸳鸯瓦，旧时屋瓦一伏一仰，片片相扣故有此称。", "伤春罢：感伤春天逝去。", "数：计算。梧桐叶下：代表秋天来临。"], "background": "这首词作于1905年的秋天，王国维作为一个文人，也很关心国家大事，因为他所忠于的清王朝如同他描写的秋叶一样，飘零而下，王国维也为此忧心忡忡。但王国维当时只是一个学校教员，生活也是相当的拮据，所以借这首词表达自己对国事和自己命运前途的担忧。"},
{"title": "青玉案·江南秋色垂垂暮", "author": "王国维", "paragraphs": "江南秋色垂垂暮，算幽事，浑无数。日日沧浪亭畔路。西风林下，夕阳水际，独自寻诗去。\t可怜愁与闲俱赴。待把尘劳截愁住。灯影幢幢天欲曙。闲中心事，忙中情味，并入西楼雨。", "topic": "秋天", "notes": ["青玉案：以", "《青玉案·凌波不过横塘路》为正体，双调六十七字，前后段各六句、五仄韵。另有双调六十七字，前后段各六句、四仄韵；双调六十八字，前后段各六句、四仄韵等十二种变体。", "垂垂：渐渐地。", "幽事：幽景，胜景。", "浑：仍旧，仍然。", "沧浪亭：在苏州城南。词人曾在苏州长期居住。", "俱赴：指忧愁和悠双往往一同涌上心头。", "截愁住：截住愁的倒装句。", "幢幢（chuáng）：形容灯光摇摆不定。"], "background": "光绪三十年（1904年），王国维在江苏师范学堂任教，讲授伦理学课程，并研究叔本华、康德哲学。这首《青玉案》就是他试图在文学中“求直接之慰藉”的自我感觉之作。"},
{"title": "浣溪沙·霜落千林木叶丹", "author": "王国维", "paragraphs": "霜落千林木叶丹。远山如在有无间。经秋何事亦孱颜。\t且向田家拚泥饮，聊从卜肆憩征鞍。只应游戏在尘寰。", "topic": "秋天", "notes": ["1、千常：大量树常。千，泛指多数。", "2、木叶丹：指在秋季变红2树叶。木叶，树叶。", "3、何事：为什么。", "4、孱（chán）颜：形容山2高峻不齐2样子。", "5、拚（pàn）：不顾一切2干。", "6、泥饮（nì yǐn）：强留饮酒。此处亦有久饮、痛饮之意。", "7、卜肆（sì）：卖卜2铺子。", "8、憩（qì）征鞍：旅途中休息。征鞍：旅行时骑乘2马匹。", "9、游戏在尘寰（huán）：游戏人间，有玩世不恭意。尘寰：指人世间。"], "background": ""},
{"title": "浣溪沙·已落芙蓉并叶凋", "author": "王国维", "paragraphs": "已落芙蓉并叶凋。半枯萧艾过墙高。日斜孤馆易魂消。\t坐觉清秋归荡荡，眼看白日去昭昭。人间争度渐长宵。", "topic": "秋天", "notes": ["浣溪沙：唐代教坊曲名，后用为词牌。分平仄两体，字数以四十二字居多，还有四十四字和四十六字两种。", "芙蓉：荷花的别名。", "萧艾：艾蒿，臭草。", "孤馆：孤寂的客舍。", "清秋：明净爽朗的秋天。", "白日去昭昭：白日指太阳，阳光。昭昭指明亮。", "争度：怎么渡过。渐长宵：一天比一天长的夜晚。"], "background": "此词写于1908年秋，北京。王国维在这年正月续娶潘丽正为妻。三月，王国维携妻北上，潘氏操持家政，王国维有心治学。"},
{"title": "诉衷情·凭觞静忆去年秋", "author": "晏几道", "paragraphs": "凭觞静忆去年秋，桐落故溪头。诗成自写红叶，和恨寄东流。\t人脉脉，水悠悠。几多愁。雁书不到，蝶梦无凭，漫倚高楼。", "topic": "秋天", "notes": "", "background": ""},
{"title": "秋霁", "author": "崔道融", "paragraphs": "雨霁长空荡涤清，远山初出未知名。\t夜来江上如钩月，时有惊鱼掷浪声。", "topic": "秋天", "notes": ["霁：雨过天晴。", "荡涤：冲洗。"], "background": ""},
{"title": "小梁州·秋", "author": "贯云石", "paragraphs": "芙蓉映水菊花黄，满目秋光。枯荷叶底鹭鸶藏。金风荡，飘动桂枝香。〔幺〕雷峰塔畔登高望，见钱塘一派长江。湖水清，江湖漾，天边斜月，新雁两三行。", "topic": "秋天", "notes": ["正宫：宫调名，元曲常用宫调。小梁州：曲牌名。属正宫，亦入中吕、南调。有幺篇换头，须连用。与诸宫调《梁州》略同。", "鹭鸶：即白鹭，一种水鸟。", "金风：即秋风。", "幺：即幺篇，戏曲、散曲术语。连续使用同一曲牌时，后面各曲不再标出曲牌名，而写作“幺篇”或“幺”。", "雷峰塔：五代时吴越王", "妃黄氏建，遗址在今西湖南夕照山上。"], "background": "此曲为贯云石晚年隐居杭州时所作。延祐、至治（公元1314—1323年）年间，贯云石隐居杭州。他对杭州怀有深切的感情，因作此词以咏西湖之景。"},
{"title": "金盏子·赋秋壑西湖小筑", "author": "吴文英", "paragraphs": "卜筑西湖，种翠萝犹傍，软红尘里。来往载清吟，为偏爱吾庐，画船频繁。笑携雨色晴光，入春明朝市。石桥锁，烟霞五百名仙，第一人是。\t临酒论深意。流光转、莺花任乱委。冷然九秋肺腑，应多梦、岩扃冷云空翠。漱流枕石幽情，写猗兰绿绮。专城处，他山小队登临，待西风起。", "topic": "秋天", "notes": ["酒：一作“醉”。", "猗：一作“漪”。", "专：一作“转”。"], "background": "贾似道，字秋壑，理宗时为丞相兼枢密使；度宗立拜太师，封魏国公，赐第葛岭，权倾朝野。吴文英因有一兄弟翁应龙为贾的堂吏，故得他中介，有词投献似道。贾似道西湖小筑在南屏。此词作于贾为荆湖制置使时。参阅《水龙吟·过秋壑湖上旧居寄赠》词。"},
{"title": "浣溪沙·消息谁传到拒霜", "author": "纳兰性德", "paragraphs": "消息谁传到拒霜？两行斜雁碧天长，晚秋风景倍凄凉。\t银蒜押帘人寂寂，玉钗敲烛信茫茫。黄花开也近重阳。", "topic": "秋天", "notes": ["浣溪沙：唐教坊曲名，因春秋时期人西施浣纱于若耶溪而得名，后用作词牌名，又名“浣溪纱”“小庭花”等。此调有平仄两体。全词分上下两片，上片三句全用韵，下片末二句用韵，过片二句用对偶句的居多。音节明快，句式整齐，易于上口，为婉约派与豪放派多数词人所常用。", "拒霜：木芙蓉花，俗称芙蓉或芙蓉花，仲秋开花，耐寒不落，故名。", "银蒜：银制的蒜形帘押。", "玉钗敲竹：用玉钗轻轻敲竹，表示心事难耐，借以排遣愁怀。一作“玉钗敲烛”。"], "background": "这首词作于康熙年间。词人在重阳节到来之时，为了抒发对往日情人的思念之情，故作下此词。"},
{"title": "长相思·秋眺", "author": "朱栴", "paragraphs": "水悠悠，路悠悠，隐隐遥山天尽头，关河又阻修。\t古兴州，古灵州，白草黄云都是愁，劝君休倚楼。", "topic": "秋天", "notes": [], "background": ""},
{"title": "虞美人·秋感", "author": "吴文英", "paragraphs": "背庭缘恐花羞坠。心事遥山里。小帘愁卷月笼明。一寸秋怀禁得、几蛩声。\t井梧不放西风起。供与离人睡。梦和新月未圆时。起看檐蛛结网、又寻思。", "topic": "秋天", "notes": ["缘：因为。", "蛩（qióng）：此处指蟋蟀。", "井梧：井边的梧桐。唐女诗人薛涛有《井梧吟》诗。", "檐蛛：屋檐下的蜘蛛。"], "background": ""},
{"title": "庆春宫·秋感", "author": "吴文英", "paragraphs": "残叶翻浓，余香栖苦，障风怨动秋声。云影摇寒，波尘锁腻，翠房人去深扃。昼成凄黯，雁飞过、垂杨转青。阑干横暮，酥印痕香，玉腕谁凭。\t菱花乍失娉婷。别岸围红，千艳倾城。重洗清杯，同追深夜，豆花寒落愁灯。近欢成梦，断云隔、巫山几层。偷相怜处，熏尽金篝，销瘦云英。", "topic": "秋天", "notes": ["庆春宫：词牌名，即《高阳台》的变体，双调，一百二字，上、下片各十一句，上片四平韵，下片五平韵。", "谁：一本作“难”。", "熏：一本作“重”。"], "background": ""},
{"title": "清平乐·秋光烛地", "author": "陈师道", "paragraphs": "秋光烛地。帘幕生秋意。露叶翻风惊鹊坠。暗落青林红子。\t微行声断长廊。熏炉衾换生香。灭烛却延明月，揽衣先怯微凉。", "topic": "秋天", "notes": "", "background": ""},
{"title": "烛影摇红·越上霖雨应祷", "author": "吴文英", "paragraphs": "秋入灯花，夜深檐影琵琶语。越娥青镜洗红埃，山斗秦眉妩。相间金茸翠亩。认城阴、春耕旧处。晚舂相应，新稻炊香，疏烟林莽。\t清磬风前，海沈宿袅芙蓉炷。阿香秋梦起娇啼，玉女传幽素。人驾梅槎未渡。试梧桐、聊分宴俎。采菱别调，留取蓬莱，霎时云住。", "topic": "秋天", "notes": ["沈：即“沉”。", "梅：一本作“海”。"], "background": "“越”，指绍兴。“霖雨”，即多雨也。由词题“越上霖雨应祷”句看来，此词作于公元1246年（即宋理宗淳祐六年，据夏承焘《吴梦窗系年》，词人四十七岁）以后，他往来于杭、越之间的时候。"},
{"title": "蝶恋花·月到东南秋正半", "author": "王国维", "paragraphs": "月到东南秋正半。双阙中间，浩荡流银汉。谁起水精帘下看。风前隐隐闻箫管。\t凉露湿衣风拂面。坐爱清光，分照恩和怨。苑柳宫槐浑一片。长门西去昭阳殿。", "topic": "秋天", "notes": ["双阙，古代宫殿前的高建筑物，左右各一，建成高台，台上起楼观。以二阙之间有空缺，故名双阙。", "水精帘，形容质地精细而色泽莹澈的帘子。", "苑柳宫槐，喻承雨露之恩者。", "昭阳殿，汉成帝皇后赵飞燕所居，因以指得宠者承恩之处。"], "background": ""},
{"title": "诉衷情·送述古迓元素", "author": "苏轼", "paragraphs": "钱塘风景古来奇，太守例能诗。先驱负弩何在，心已誓江西。\t花尽后，叶飞时。雨凄凄。若为情绪，更问新官，向旧官啼。", "topic": "秋天", "notes": ["诉衷情，词牌名，唐教坊曲。唐", "取《离骚》“众不可户说兮，孰云察余之中情”之意，创制此调。双调四十四字，上下片各三平韵。", "迓（yà）：迎接。元素：杨绘，字元素，绵竹（今属四川）人。宋仁宗皇祐年间中进士及第。宋神宗熙宁七年（1074年）六月，自应天府（今河南商丘）移知杭州，八月到任。述古：陈襄，字述古，号古灵先生，侯官（今福建福州）人。北宋理学家、“海滨四先生”之首，宋仁宗、宋神宗时期名臣。宋神宗熙宁七年（1074年）罢任杭州知州，赴陈州任知州。", "“太守”句：傅干注：“白乐天（居易）为杭州太守，善诗。初，乐天为苏守，", "以诗寄乐天云：“苏州太守（当作“刺史”）例能诗，西掖（yè）吟（当作“今”）来替左司。”", "先驱负弩：指在前面迎候的官员。出自《史记·", "列传》：“天子以为然，乃拜相如为中郎将，建节往使。……至蜀，蜀太守以下郊迎，县令负弩矢先驱，蜀人以为宠。”负弩（nǔ）：背着硬弓。弩，用机械发射的弓。", "誓江西：誓江作浙江，这里指钱塘江。西，向西面飞，此处活用为动词。", "若为情绪：等于说何以为情，或难以为情。按此句与后二句为倒文，应当依照“更问新官，向旧官啼，若为情绪”这一语序来解释。", "更问二句：原南朝陈代乐昌公主诗：“此日何迁次，新官对旧官。笑啼俱不敢，方验作人难。”按“新官”指后夫隋越国公", "，“旧官”指前夫陈太子舍人徐德言。 “更问”二句，互文，“新官”、“旧官”前后互相包涵。“向旧官啼”，当是“新官对旧官，笑啼俱不敢”的省文。"], "background": "宋神宗熙宁七年（1074年）七月。杭州知州陈襄罢任，新任知州杨绘正在赴杭州途中，杭州官妓前往苏州迎接杨绘，苏轼作该词描绘迎接的场面。"},
{"title": "青玉案·与朱景参会北岭", "author": "陆游", "paragraphs": "西风挟雨声翻浪。恰洗尽、黄茅瘴。老惯人间齐得丧。千岩高卧，五湖归棹，替却凌烟像。\t故人小驻平戎帐，白羽腰间气何壮。我老渔樵君将相。小槽红酒，晚香丹荔，记取蛮江上。", "topic": "秋天", "notes": ["青玉案：词牌名，取于东汉", "《四愁诗》：“美人赠我锦绣段，何以报之青玉案”一诗。又名《横塘路》、《西湖路》，双调六十七字，前后阕各五仄韵，上去通押。", "朱景参：名孝闻，时为福州宁德县县尉。北岭：山名，在福州和宁德之间。", "声翻浪：声音像波涛翻滚一样。", "黄茅瘴：《番禺杂编》谓八、九月为黄茅瘴。", "“千岩高卧 ”三句：前两句虚写自己退隐的形象。唐太宗贞观十七年（643年），诏画功臣二十四人于凌烟阁。", "指出自己愿意退隐，不追求画像凌烟阁。", "故人：指朱景参。平戎（róng）帐：军帐。", "白羽：箭名。唐太宗为秦王时，以大白羽射中单雄信枪刃，见《酉阳杂俎》。", "小槽（cáo）：压酒的器具。", "诗：“小槽酒滴真珠红。”", "晚香丹荔（lì）：指晚红，荔枝的品种之一，熟时最迟。", "蛮江：指闽江。"], "background": "宋绍兴二十八年（1158），陆游任宁德县（在今福建）主簿，与县尉朱景参情好甚笃。词人与朱景参游览北岭的时候，写下了这首词。"},
{"title": "玉京秋·烟水阔", "author": "周密", "paragraphs": "长安独客，又见西风，素月丹枫凄然其为秋也，因调夹钟羽一解\t烟水阔。高林弄残照，晚蜩凄切。碧碪度韵，银床飘叶。衣湿桐阴露冷，采凉花、时赋秋雪。叹轻别。一襟幽事，砌蛩能说。\t客思吟商还怯。怨歌长、琼壶暗缺。翠扇恩疏，红衣香褪，翻成消歇。玉骨西风，恨最恨、闲却新凉时节。楚箫咽。谁倚西楼淡月。", "topic": "秋天", "notes": ["长安：此处借指南宋都城临安。", "夹钟羽一解：夹钟羽，一种律调。一解，一阙。", "晚蜩句：", "《雨霖铃》：“寒蝉凄切，对长亭晚，骤雨初歇。”蜩，蝉。", "碧砧句：有青苔的石砧传来有节奏的捣衣声，井旁落满枯黄的桐叶。银床，井上辘轳架。古乐府《淮南王篇》：“后园作井银作床，金瓶素绠汲寒浆。”", "《九日传宴》诗：“玉醴吹岩菊，银床落井桐。”", "凉花：指菊花、芦花等秋日开放的花，此地系指芦花。", "《早秋》诗：“早藕擎霜节，凉花束紫梢。”", "秋雪：指芦花，即所采之凉花。", "砌蛩：台阶下的蟋蟀。", "吟商：吟咏秋天。商，五音之一，《礼记·月令》：“孟秋之月其音商。”", "琼壶暗缺：敲玉壶为节拍，使壶口损缺。", "翠扇恩疏：由于天凉，主人已捐弃扇子。", "红衣句：古代女子有赠衣给情人以为表记的习俗；", "《九歌·湘夫人》：“捐余袂兮江中，遗余褋兮醴浦。”", "楚箫咽：相传为", "所写《忆秦娥》词：“箫声咽，秦娥楚断秦楼月。”", "谁倚：各本作“谁寄”，此从《词综》卷十九、知不足斋丛书本《苹洲渔笛谱》。"], "background": ""},
{"title": "重叠金·壬寅立秋", "author": "黄升", "paragraphs": "西风半夜惊罗扇。蛩声入梦传幽怨。碧藕试初凉。露痕啼粉香。\t清冰凝簟竹。不许双鸳宿。又是五更钟。鸦啼金井桐。", "topic": "秋天", "notes": ["蛩：蟋蟀。", "金井：妆饰讲究的井台。"], "background": ""},
{"title": "醉蓬莱·渐亭皋叶下", "author": "柳永", "paragraphs": "渐亭皋叶下，陇首云飞，素秋新霁。华阙中天，锁葱葱佳气。嫩菊黄深，拒霜红浅，近宝阶香砌。玉宇无尘，金茎有露，碧天如水。\t正值升平，万几多暇，夜色澄鲜，漏声迢递。南极星中，有老人呈瑞。此际宸游，凤辇何处，度管弦清脆。太液波翻，披香帘卷，月明风细。", "topic": "秋天", "notes": ["醉蓬莱：词牌名，", "自度曲。双调九十七字，上片十一句、下片十二句各四仄韵。", "亭皋（gāo），水边的平地。陇首，泛指高山之巅。", "素秋：秋季。古代五行之说，秋属金，其色白，故称素秋。新霁（jì）：雨雪后初晴。", "华阙中天：意谓华美的皇宫耸入高空。中天，高空。", "锁：笼罩。葱葱：气象旺盛的样子。", "拒霜：木芙蓉花的别称。冬凋夏茂，仲秋开花，耐寒不落，故名。", "宝阶香砌：喻台阶之美且香。", "玉宇：华丽的宫殿。", "金茎：用以擎承露盘的铜柱。", "升平：太平盛世。", "万几：也作万机，指皇帝日常处理的纷繁政务。", "澄鲜：清新。", "漏声迢递：意谓漏声传到很远的地方。漏声，计时漏壶的滴水声。迢递，遥远。", "宸（chén）游：帝王之巡游。宸，北极星所在为宸，后借用为皇帝所居，引申为帝王的代称。", "凤辇（niǎn）：皇帝的车驾。", "度：按曲谱奏曲。管弦：管乐器和弦乐器，泛指乐器。", "太液，太液池，又名蓬莱池，始建于汉武帝时，在长安建章宫北。此借指宋汴京宫中池苑。披香，即披香殿，汉代宫殿名。此借指宋汴京宫中殿宇。"], "background": "关于此词的具体创作时间无法考证，有一种说法是，北宋文人王辟之在《渑水燕谈录》有一段记载，认为此词作于皇祐年间（1049—1053年），唐圭璋在《柳永事迹新证》里首肯此说。"},
{"title": "四园竹·浮云护月", "author": "周邦彦", "paragraphs": "浮云护月，未放满朱扉。鼠摇暗壁，萤度破窗，偷入书帏。秋意浓，闲伫立，庭柯影里。好风襟袖先知。\t夜何其。江南路绕重山，心知漫与前期。奈向灯前堕泪，肠断萧娘，旧日书辞犹在纸。雁信绝，清宵梦又稀。", "topic": "秋天", "notes": ["浮云护月：指月亮被薄云遮盖。", "《季秋苏五弟缨江夜宴》诗：“明月生长好，浮云薄渐遮。”", "朱扉（fēi）：红漆的门。", "鼠摇暗壁：老鼠在壁角暗处恣意活动。这是化用", "《登宝公塔》诗：“鼠摇岑寂声随起”和崔涂《秋夕与王处士话别》诗：“虫声移暗壁，月色懂寒条。” [3]  ④“萤度”二句：化用唐僧", "《萤》诗：“透窗穿竹住还移……夜深飞过读书帏。”", "庭柯：庭院里的树木。", "《归去来兮辞》：“眄庭柯以怡颜。”", "“好风”句：化用", "《秋思》诗：“微雨池塘见，好风襟袖知。”", "夜何其：夜深已是什么时候？语本：《诗经·小雅·庭燎》：“夜如何其？夜未央。”", "漫：枉然，徒然。指心中已不存希望。前期：早先的期约。", "奈：无奈。", "“肠断”二句：化用唐杨巨源《崔娘》诗：“风流才子多春思，肠断萧娘一纸书。”萧娘，这里代指作者所爱的美人。", "雁信绝：书信断绝。古有鸿雁传书的传说。"], "background": "此词创作于元祐二年至绍圣四年之间，当时周邦彦再旅汴京之时所作，这也是一首抒写羁旅哀愁的词。"},
{"title": "昭君怨·暮雨丝丝吹湿", "author": "纳兰性德", "paragraphs": "暮雨丝丝吹湿，倦柳愁荷风急。瘦骨不禁秋，总成愁。\t别有心情怎说，未是诉愁时节，谯鼓已三更，梦须成。", "topic": "秋天", "notes": ["昭君怨：词牌名，又名“洛妃怨”“宴西园”等，双调，四十字，前后段各四句，两仄韵，两平韵。", "倦柳愁荷：此谓秋色已浓。", "不禁：不能经受。", "谯（qiáo）鼓：古代谯楼（城门之上的了望楼）上的更鼓。", "须：即“应”。"], "background": "纳兰性德对表妹情深之至，但其表妹最终辗转进宫。是夜，作者独看暮雨丝丝，秋雨凄苦，夜风凉，薄凌厉，柳树、荷花也倦极愁极，于是作者由这凄风苦雨，生出对表妹的无尽相思愁绪来。就是在这种煎熬中，作者创作了这首词以表达相思愁绪。"},
{"title": "沉醉东风·山对面蓝堆翠岫", "author": "赵善庆", "paragraphs": "山对面蓝堆翠岫，草齐腰绿染沙洲。傲霜橘柚青，濯雨蒹葭秀，隔沧波隐隐江楼。点破潇湘万顷秋，是几叶儿传黄败柳。", "topic": "秋天", "notes": ["沉醉东风：曲牌名。", "湘阴：今湖南湘阴，在湘江下游，洞庭湖南岸。", "蓝：蓼蓝，一种可制作染料的草。", "岫（xiù）：山峰。", "濯（zhuó）：冲洗。", "潇湘：潇水、湘水，湖南的两条大江。此处以潇湘指洞庭湖一带。"], "background": "该词具体创作年份未知。在某个秋日，诗人行走在湘（今湖南）阴道上，看到美丽宜人的秋景，便忍不住自己内心的喜悦，有感而发，写下了这首小令。"},
{"title": "长相思·铁瓮城高", "author": "秦观", "paragraphs": "铁瓮城高，蒜山渡阔，干云十二层楼。开尊待月，掩箔披风，依然灯火扬州。绮陌南头，记歌名宛转，乡号温柔。曲槛俯清流。想花阴，谁系兰舟？\t念凄绝秦弦，感深荆赋，相望几许凝愁。勤勤裁尺素，奈双鱼难渡瓜洲。晓鉴堪羞，潘鬓点、吴霜渐稠。幸于飞、鸳鸯未老，不应同是悲秋。", "topic": "秋天", "notes": ["相思：《疆邮丛书》本《贺方回词》此调作《望扬州》，“掩箔”作“卷箔”、“绮陌”作“绣陌”。", "铁瓮（wèng）：镇江（今属江苏）古城名，三国时孙权所筑。子城，指附属于大城的内城。", "蒜山渡：蒜山渡口。", "干云十二层楼：镇江城楼有十二层高，故曰干云。干云：冲云。干，冲。", "开尊待月：斟上酒等待月亮升起。尊同樽，古代盛酒的器具。", "掩箔（bó）披风：放下竹帘，当风而立。箔，竹帘子。披风，挡风。披，本指分散，此处引申为遮挡。", "绮（qǐ）陌：纵横交错的道路。", "歌名宛转：指《宛转歌》，一名《神女宛转歌》。", "乡号温柔：即温柔乡。", "兰舟：即木兰舟。任坊《述异记》卷下：“木兰川在浔阳江中，多木兰树。昔吴王阖闾植木兰于此，用构宫殿也。七里洲中有鲁班刻木兰为舟，舟至今在洲中。诗家云‘木兰舟’出于此。”唐", "《楚江怀古》诗：“猿啼洞庭树，人在木兰舟。”宋", "《鹧鸪天》：“守得莲开结伴游，约开萍叶上兰舟。”", "秦弦：即秦筝，古代弦乐器，音调凄苦。相传为秦时蒙恬所造。秦", "《谏逐客书》：“夫击瓮叩缶，弹筝搏髀，而歌呼呜呜快耳目者，真秦之声也。”唐", "《古风五十九首》之五十五：“齐瑟弹东吟，秦弦弄西音。”", "荆赋：指《楚辞》。楚，古称为荆。联系结句，知此指", "《九辩》。", "凝愁：《诗词曲语辞汇释》卷五：“凝，为一往情深专注不已之义，犹今所云‘发痴’、‘发怔’、“出神’、‘失魂’也，……", "《八声甘州》词：‘争知我，凭阑干处，正恁凝愁。’凝愁，愁之不已，犹云‘深愁’也。”", "勤勤二句：尺素，指书信，古代以生绢作书，故名。双鱼，指鱼形信函。", "瓜洲，在今江苏扬州南四十里长江边，隔岸与镇江相对，亦作“瓜州”。", "晓鉴：早起临镜。唐", "《无题》诗：“晓镜但愁云鬓改，夜吟应觉月光寒。”", "吴霜，唐", "《还自会稽歌》：“吴霜点归鬓，身与塘蒲晚。”", "幸：幸亏之意。", "于飞：指夫妇好合。于飞，比翼而飞，喻夫妇好合。鸳鸯，指情侣或夫妇。", "悲秋：秋气萧森，令人伤感，故称。"], "background": "秦观曾于熙宁九年访湖州李公择归来，经镇江；宋元丰七年（1084年）八月十九日与滕元发等会苏轼于金山，十月复来，作《宿金山》《金山晚眺》二诗，可见对镇江形胜甚为熟悉。此词至迟作于宋元丰七年（1083年）之秋。"},
{"title": "迷神引·红板桥头秋光暮", "author": "柳永", "paragraphs": "红板桥头秋光暮。淡月映烟方煦。寒溪蘸碧，绕垂杨路。重分飞，携纤手、泪如雨。波急隋堤远，片帆举。倏忽年华改，向期阻。\t时觉春残，渐渐飘花絮。好夕良天长孤负。洞房闲掩，小屏空、无心觑。指归云，仙乡杳、在何处。遥夜香衾暖，算谁与。知他深深约，记得否。", "topic": "秋天", "notes": ["迷神引：词牌名，", "自制曲，《乐章集》注“中吕调”。双调九十七字，上片十一句六仄韵，下片十三句六仄韵。", "红板桥：有泛指和专指，泛指谓红色栏杆之桥，专指则谓汴京顺天门外之板桥。从词中所写，知其为专指。秋光暮：秋天的夜晚。", "烟：雾气。煦（xù）：温暖；暖和。", "寒溪蘸碧：寒冷的溪水如同蘸了染料一样清澈。寒：微微的秋寒。", "垂杨：即垂柳，古人将杨柳混称，故云。", "重（chóng）分飞：重新回忆起当初分别时的情景。分飞，分别。", "隋堤：汴河大堤，因筑于隋代，故名。", "倏忽：忽然，时间过得很快。", "向期阻：怎奈归期却被阻隔。向，怎向。", "花絮：柳絮。", "孤负：辜负。孤，古同“辜”。", "小屏：即小屏风，室内陈设物，亦有置于炕头者，谓之炕屏，能映人影。", "仙乡：仙人所居处，借称所爱者的居处。", "遥夜：长夜。"], "background": "柳永秋季离开汴京者只有两次：一次是少年远游时，一次是庆历四年自苏州赴成都经汴京时。但庆历四年为西行，而词中谓“波急隋堤远”显然为南行之证，据此，知此词写于柳永少年远游江浙时的第二年春天。"},
{"title": "诉衷情·秋情", "author": "吴文英", "paragraphs": "片云载雨过江鸥。水色澹汀洲。小莲玉惨红怨，翠被又经秋。\t凉意思，到南楼。小帘钩。半窗灯晕，几叶芭蕉，客梦床头。", "topic": "秋天", "notes": ["诉衷情：唐教坊曲名，后用作词调。又名作“步花间”“桃花水”“偶相逢”“画楼空”“试周郎”“一丝风”。分单双调两体。单调三十三字，九句，平、仄韵互用，六平韵为主，二仄韵两部错叶。双调，四十字，上片四句三平韵，下片六句三平韵。也有四十一字至四十五字等体。《梦窗词集》诸词，为四十四字体。", "澹：亦写作“淡”。"], "background": ""},
{"title": "解连环·秋情", "author": "吴文英", "paragraphs": "暮檐凉薄。疑清风动竹，故人来邈。渐夜久、闲引流萤，弄微照素怀，暗呈纤白。梦远双成，凤笙杳、玉绳西落。掩綀帷倦入，又惹旧愁，汗香阑角。\t银瓶恨沉断索。叹梧桐未秋，露井先觉。抱素影、明月空闲，早尘损丹青，楚山依约。翠冷红衰，怕惊起、西池鱼跃。记湘娥、绛绡暗解，褪花坠萼。", "topic": "秋天", "notes": ["解连环：又名“望梅”“杏梁燕”。计三体。此用正体，双调一百零六字，上片十一句五仄韵，下片十句五仄韵。", "凉薄：微凉。", "邈（miǎo）：远，渺茫。", "流萤（yíng）：飞行无定的萤。", "《秋夕》诗：“银烛秋光冷画屏，轻罗小扇扑流萤。”", "素怀：平素的抱负。", "双成：董双成，传说为西王母的侍女。", "凤笙（shēng）：笙的美称。笙形如凤凰，音如凤鸣。", "玉绳：天乙、太乙两星之共名。在北斗第五星玉衡北面。秋季夜半，玉绳自西北转，逐渐下沉，故古人多以玉绳低垂形容夜深或拂晓。", "綀（shū）帷：粗布制成的帷幔。", "露井：指无井盖、井栏之井。", "明月：指团扇。", "丹青：本指绘画用的材料，后泛指绘画。", "楚山：代指美女双眉。", "西池：指苏州西园中之池。一说指西湖。", "湘娥：湘夫人。", "绛绡（jiàng xiāo）暗解：即“香囊暗解”。", "萼：花萼。花瓣下部的一圈绿色小片。"], "background": "吴文英早年在苏州结识某女子。他们的爱情以悲剧告终。吴文英对她的情感是真挚深厚的，他在词作里常以极隐讳的笔法抒写无尽的哀怨。这首词是词人寓居苏州的后期、在其恋爱悲剧发生之后作的。充分抒发出作者的一腔忧怨之情。"},
{"title": "谒金门·秋兴", "author": "苏轼", "paragraphs": "秋池阁。风傍晓庭帘幕。霜叶未衰吹未落。半惊鸦喜鹊。\t自笑浮名情薄。似与世人疏略。一片懒心双懒脚。好教闲处著。", "topic": "秋天", "notes": ["谒金门：词牌名。唐教坊曲名，后用为词调。又名《不怕醉》、《出塞》。", "秋池阁：秋天的花园楼阁。", "傍：伴随。晓：晨光。并作动词用，有破晓之意。", "衰：凋枯。", "半：量词，这里引伸为微微。", "似：好似，几乎。疏略：疏远，忘却，不往来。", "好教：好使。著：置放。"], "background": "此词作于宋神宗熙宁六年（1073年）秋，是时，东坡在杭州通守任上。与《谒金门·秋夜》一样，此词系东坡与人酬赠之作。"},
{"title": "普天乐·翠荷残", "author": "滕宾", "paragraphs": "翠荷残，苍梧坠。千山应瘦，万木皆稀，蜗角名，蝇头利。输与渊明陶陶醉，尽黄菊围绕东篱。良田数顷，黄牛二只，归去来兮。", "topic": "秋天", "notes": ["蜗角名：如同蜗角那样的虚名，比喻渺小不足道的浮世虚名。", "蝇头利：如同苍蝇头那样的小利。比喻非常微小的利润。"], "background": ""},
{"title": "忆仙姿·莲叶初生南浦", "author": "贺铸", "paragraphs": "莲叶初生南浦，两岸绿杨飞絮。向晚鲤鱼风，断送彩帆何处？凝伫，凝伫，楼外一江烟雨。", "topic": "秋天", "notes": ["忆仙姿：词牌名，即《如梦令》，还有一个名字《宴桃园》。五代时后唐庄宗李存勗创制。", "南浦：面南的水边。", "向晚：傍晚。鲤鱼风：指九月风。", "断送：送走。", "凝伫：指发愣发呆，久立凝望。"], "background": "贺铸本卫州共城（今河南辉县）人，曾在和州（今安徽和县）、泗州（今江苏盱眙）、太平州（今安徽当涂）等处任职。这些地方，均近江临淮，晚年又退居苏州，长居水乡，在他的词集中，便有不少写水乡风光与生活的作品，《忆仙姿》即其中一首。"},
{"title": "谒金门·秋已暮", "author": "牛希济", "paragraphs": "秋已暮，重叠关山岐路。嘶马摇鞭何处去，晓禽霜满树。\t梦断禁城钟鼓，泪滴枕檀无数。一点凝红和薄雾，翠蛾愁不语。", "topic": "秋天", "notes": ["谒金门：词牌名。", "关山；泛指关塞和山岳。歧路：岔道。", "禁城：宫城。", "枕檀：即檀枕。", "凝红：指溶有脂粉的眼泪。", "翠蛾：指女子黑而细长的眉毛。"], "background": ""},
{"title": "华胥引·秋思", "author": "周邦彦", "paragraphs": "川原澄映，烟月冥濛，去舟如叶。岸足沙平，蒲根水冷留雁唼。别有孤角吟秋，对晓风呜轧。红日三竿，醉头扶起还怯。\t离思相萦，渐看看、鬓丝堪镊。舞衫歌扇，何人轻怜细阅。点检从前恩爱，但凤笺盈箧。愁剪灯花，夜来和泪双叠。", "topic": "秋天", "notes": ["华胥引：此调为", "始创。陈本注“黄钟”宫，题作“秋思”，《百家词》同。", "冥濛：昏暗迷茫。", "唼（shà）：水鸟或鱼类吞食。", "别有孤角吟秋，对晓风呜轧（yà）：此句化用", "《题齐安城楼》诗中“鸣轧江楼角一声，微阳潋潋落寒汀”的句子。", "相萦（yíng）：相互缠绕。", "鬓丝堪镊（niè）：鬓发稀白，已不堪夹镊。镊：镊子，拔除毛发的用具，此作动词“拔除”解。", "点检：即检点。", "凤笺盈箧（qiè）：谓书箱里装满昔日的书信和诗笺。凤笺（jiān）：信纸的美称，指绘有金凤的纸。箧，小箱子，如书箧，行箧。", "灯花：灯芯余烬结成的花形。", "和泪双叠：谓含泪看灯花，花形两两相叠。"], "background": "据清代词学家黄苏《蓼园词选》记载，周邦彦晚年不愿与蔡京奸党合作，被逐出朝廷，由徽猷阁待制出知顺昌府、处州等地，此词或在顺昌府、处州两地写成。"},
{"title": "清平乐·秋词", "author": "苏轼", "paragraphs": "清淮浊汴。更在江西岸。红旆到时黄叶乱。霜入梁王故苑。\t秋原何处携壶。停骖访古踟蹰。双庙遗风尚在，漆园傲吏应无。", "topic": "秋天", "notes": ["清平乐：词牌名。唐教坊曲。一名《醉东风》、《忆萝月》。双调小令，平仄韵转换格。", "秋词：傅本词题作“送述古赴南都”可从。南都：今河南商丘市。", "清淮浊汴：清淮，清澈的淮河水。淮河为古代四渎之一，源出河南桐柏山，东流入安徽，注入洪泽湖，下游自淮阴县与大运河会合。古汴，汴河故道有两条，这里是指隋以后汴河故道，由河南的旧郑州、开封至商邱县治南，改东南流经安徽的宿县、灵璧、泗县入淮河。现在已荒废，只有泗县尚有汴水断渠。", "江西：古时泛称长江以南为江东或江左，长江以北为江西或江右。", "红旆（pèi）：红旗。此指太守的仪仗。", "梁王故苑：汉代梁孝王刘武在陈留（今河南开封市东南）修治的宫室园林。", "携壶：带着酒壶。这里有游赏的意思。", "停骖（cān）：停住车马。骖，一车驾三马或驾车时位于两旁的马。", "踟蹰（chí chú）：心中犹疑，要走不走的样子", "双庙：唐代安史之乱时，", "、许远坚守雎阳（今河南商丘），最后都壮烈牺牲，后人立二祠，称为双庙。", "漆园傲吏：指", "。庄周是战国时期的思想家，道家学派主要代表人物之一，曾经做过漆园吏，抱有傲视王侯，不为名利所动的人生态度。"], "background": "该词应写于宋神宗熙宁七年甲寅（1074年），当时苏轼任杭州通判时的同僚与好友陈襄（字述古）移守南都（今河南商丘）。词中预计陈襄到时已“黄叶乱”，有“霜”，该词大约作于初秋，陈襄即将离杭州时。"},
{"title": "好事近·杭苇岸才登", "author": "周之琦", "paragraphs": "杭苇岸才登，行入乱峰层碧。十里平沙浅渚，又渡头人立。笋将摇梦上轻舟，舟尾浪花湿。恰好乌篷小小，载一肩秋色。", "topic": "秋天", "notes": ["杭苇：语出《诗·卫风·河广》：“一苇杭之。”苇原指草束，引申为小舟。　杭，通“航”。", "笋将：语出《公羊传·文公十五年》：“笋将而来也。”笋，竹舆。", "乌篷：小船，船篷竹编，漆成黑色，故称。"], "background": ""},
{"title": "生查子·秋来愁更深", "author": "杨无咎", "paragraphs": "秋来愁更深，黛拂双蛾浅。翠袖怯春寒，修竹萧萧晚。\t此意有谁知，恨与孤鸿远。小立背西风，又是重门掩。", "topic": "秋天", "notes": ["双蛾：即双眉。"], "background": ""},
{"title": "宴清都·秋感", "author": "吴文英", "paragraphs": "万里关河眼。愁凝处，渺渺残照红敛。天低远树，潮分断港，路回淮甸。吟鞭又指孤店。对玉露金风送晚。恨自古、才子佳人，此景此情多感。\t吴王故苑。别来良朋鸦集，空叹蓬转。挥毫记烛，飞觞赶月，梦销香断。区区去程何限。倩片纸、丁宁过雁。寄相思，寒雨灯窗，芙蓉旧院。", "topic": "秋天", "notes": ["宴清都：词牌名。又名“四代好”。《清真集》、《梦窗词集》并入“中吕调”。一百零二字，前片十句五仄韵，后片十句四仄韵。", "港：一本作“巷”。", "记：一本作“刻”。", "赶：一本作“趁”。", "程：一本作“情”。"], "background": ""},
{"title": "八归·秋江带雨", "author": "史达祖", "paragraphs": "秋江带雨，寒沙萦水，人瞰画阁愁独。烟蓑散响惊诗思，还被乱鸥飞去，秀句难续。冷眼尽归图画上，认隔岸、微茫云屋。想半属、渔市樵村，欲暮竞然竹。\t须信风流未老，凭持酒、慰此凄凉心目。一鞭南陌，几篙官渡，赖有歌眉舒绿。只匆匆眺远，早觉闲愁挂乔木。应难奈，故人天际，望彻淮山，相思无雁足。", "topic": "秋天", "notes": ["瞰（kàn）：俯视。", "烟蓑：捕鱼人。烟雨迷茫中身披蓑衣，指渔父。", "散响：指渔父撒网入水发出的响声。", "乱鸥：群鸥乱飞。", "隔岸：对岸。", "云屋：苍黑若云之状。", "欲暮：", "《渔翁》诗：“渔翁夜傍西岩宿营，晓汲清湘然楚竹。”然，同“燃”。", "然竹：烧竹。然，同“燃”。柳宗元《渔翁》诗：“渔翁夜傍西岩宿，晓汲清湘然楚竹。”", "凭持尊酒：凭此酒杯饮酒。", "歌眉：指歌歌女之眉。", "舒绿：舒展愁眉，古人以黛绿画眉，绿即指眉。", "乔乡：此处指故乡。", "淮山：指扬州附近之山。", "无雁足：古代传说，雁足可以传书，无雁足即谓无书信。"], "background": ""},
{"title": "小重山·秋到长门秋草黄", "author": "薛昭蕴", "paragraphs": "秋到长门秋草黄。画梁双燕去，出宫墙。玉箫无复理霓裳。金蝉坠，鸾镜掩休妆。\t忆昔在昭阳。舞衣红绶带，绣鸳鸯。至今犹惹御炉香。魂梦断，愁听漏更长。", "topic": "秋天", "notes": ["长门：长门宫。此指皇宫。", "双燕去：谓秋深。又用燕双去衬人独在。", "玉箫（xiāo）：洞箫。古人称精美物常以“玉”比喻，如“玉笛”、“玉容”、“玉楼”、“玉食”等。", "《同玉真公主过大哥山池》：“凤楼遥可见，仿佛玉箫声。”", "理：治，引申为演奏。", "霓裳（nícháng）：《霓裳羽衣曲》的略称。此曲开元天宝间盛行于宫中，", "曾因善舞此曲而受宠。", "金蝉：首饰。", "鸾（luán）镜：镜子。", "妆：装扮。", "昭阳：宫名。汉成帝宠幸的赵飞燕、赵合德姐妹即住在昭阳宫。此代指受宠时所居之所。", "绶（shòu）带：丝带。", "漏更：更漏。"], "background": "封建时代，宫女幽禁深苑、葬送青春的痛苦遭遇，是诗人笔下常见的题材。封建皇帝的后宫，有成千上万的宫女。她们一生多在深院中捱过，绝少有出宫择婚的机会，身世处境令人痛惜。此词细致准确地表现了宫中女子孤寂愁闷的心境，流露出对她们的同情。"},
{"title": "喜迁莺·霜天秋晓", "author": "蔡挺", "paragraphs": "霜天秋晓，正紫塞故垒，黄云衰草。汉马嘶风，边鸿叫月，陇上铁衣寒早。剑歌骑曲悲壮，尽道君恩须报。塞垣乐，尽櫜鞬锦领，山西年少。\t谈笑。刁斗静，烽火一把，时送平安耗。圣主忧边，威怀遐远，骄虏尚宽天讨。岁华向晚愁思，谁念玉关人老？太平也，且欢娱，莫惜金樽频倒。", "topic": "秋天", "notes": ["喜迁莺：词牌名，又名《鹤冲天》、《万年枝》、《春光好》等。", "紫塞：长城边塞。", "故垒：边塞的旧营垒。", "汉马：指宋朝边防军的战马。", "铁衣：铁甲。", "櫜（gāo）楗（jiàn）：櫜，袋子；楗，马上盛弓的器具，这里引申为收藏。", "山西：指华山或太行山以西的地区。", "刁斗：一种铜质军中用具，有柄；白天用来烧饭，夜间击以巡更。", "平安耗：报平安的消息；耗，消息、音信。", "圣主：此处指宋仁宗", "。", "岁华：时光，年华。"], "background": "宋仁宗嘉祐年间，蔡挺曾任庆州（治所在今甘肃庆阳）太守，屡次击退西夏军队的进犯，为朝廷立下大功。不久，他又调任渭州（治所在今甘肃平凉）太守，生活艰苦。在这种艰苦的环境中，蔡挺训练出一支能征惯战、训练有素的军队，保卫了国家边境的安全。于战斗间隙，蔡挺写就这篇词。"},
{"title": "苏武慢·雁落平沙", "author": "蔡伸", "paragraphs": "雁落平沙，烟笼寒水，古垒鸣笳声断。青山隐隐，败叶萧萧，天际暝鸦零乱。楼上黄昏，片帆千里归程，年华将晚。望碧云空暮，佳人何处，梦魂俱远。\t忆旧游、邃馆朱扉，小园香径，尚想桃花人面。书盈锦轴，恨满金徽，难写寸心幽怨。两地离愁，一尊芳酒凄凉，危阑倚遍。尽迟留、凭仗西风，吹干泪眼。", "topic": "秋天", "notes": ["慢：词牌名，又名选冠子，或选官子、转调选冠子、惜余春慢、仄韵过秦楼。据《御定词谱》共有十六体。词分上下两片，属于慢词。", "平沙：指广阔的沙原。", "烟笼寒水：", "《泊秦淮》诗：“烟笼寒水月笼沙。“", "古垒：古代留下的壁垒。", "鸣笳：.吹奏笳笛。笳笛，古管乐器名。", "败叶：落叶；枯叶", "片帆：孤舟；一只船。", "年华：年岁；年纪。", "碧云空暮：", "《休上人怨别》“日暮碧云合，佳人殊未来。”", "旧游：昔日的游览。", "邃馆：深院。", "朱扉：红漆门。", "香径：花间小路，或指落花满地的小径。", "桃花人面：", "《题都城南庄》“人面不知何处去，桃花依旧笑春风”。", "书盈锦铀：用苏蕙织锦回文诗事。事见《晋书·窦滔妻苏氏传》，云“窦滔妻苏氏，始平人也。名蕙，字若兰。善属文。滔，苻坚时为秦州刺史，被徙流沙。苏氏思之，织锦为回文旋图诗以赠滔，宛转循环以读之，词甚凄惋，凡八百四十字”。后用以指妻寄夫之书信。", "金徽：金饰的琴徵。徽，系弦之绳。此处代指琴。", "尊：同“樽”，古代的盛酒器具。", "危阑：高栏杆。", "迟留：停留；逗留。", "凭仗：依赖，依靠，任凭。"], "background": ""},
{"title": "青玉案·征鸿过尽秋容谢", "author": "石孝友", "paragraphs": "征鸿过尽秋容谢。卷离恨、还东下。剪剪霜风落平野。溪山掩映，水烟摇曳，几簇渔樵舍。\t芙蓉城里人如画。春伴春游夜转夜。别后知他如何也。心随云乱，眼随天断，泪逐长江泻。", "topic": "秋天", "notes": ["剪剪：形容风势轻寒。", "芙蓉城：四川成都的别称，以五代时后蜀孟昶在城上种芙蓉花而得名。"], "background": ""},
{"title": "清平乐·孤花片叶", "author": "纳兰性德", "paragraphs": "孤花片叶，断送清秋节。寂寂绣屏香篆灭，暗里朱颜消歇。\t谁怜散髻吹笙，天涯芳草关情。懊恼隔帘幽梦，半床花月纵横。", "topic": "秋天", "notes": ["香篆：即篆香，形似篆文之香。", "散髻：即解散发髻。据言此为一种发式，由南朝齐王俭所创。", "吹笙：指饮酒。", "关情：动情、牵惹情怀。唐陆龟蒙《又酬袭美次韵》：“酒香偏入梦，花落又关情。”"], "background": ""},
{"title": "风入松·麓翁园堂宴客", "author": "吴文英", "paragraphs": "一番疏雨洗芙蓉。玉冷佩丁东。辘轳听带秋声转，早凉生、傍井梧桐。欢宴良宵好月，佳人修竹清风。\t临池飞阁乍青红。移酒小垂虹。贞元供奉梨园曲，称十香、深蘸琼钟。醉梦孤云晓色，笙歌一派秋空。", "topic": "秋天", "notes": ["风入松：古琴曲有《风入松》，传为晋嵇康所作。又唐僧皎然有《风入松歌》，见《乐府诗集》卷五十九，调名由此而来。《宋史·乐志》入“林钟商”，调见晏几道《小山词》。又名“风入松慢”“远山横”。双调，七十四字、七十六字，亦有七十二字体的。前后片各六句四平韵。《梦窗词》系七十六字体。", "麓翁：即史宅之，字之仁，为宋相史弥远之子。《宁波府志》：“史子仁，心非叔父弥远所为，著《升闻录》以寓规谏。避势远嫌，退处月湖，宁宗御书‘碧沚’赐之。”“之”与“子”一字之差，《府志》不云弥远子，而为侄。宅之曾总揽朝廷财政，与吴文英为同乡。", "梧桐：一本无“梧”字。", "良：一作“凉”。"], "background": ""},
{"title": "水仙子·渡瓜洲", "author": "赵善庆", "paragraphs": "渚莲花脱锦衣收，风蓼青雕红穗秋，堤柳绿减长条瘦。系行人来去愁，别离情今古悠悠。南徐城下，西津渡口，北固山头。", "topic": "秋天", "notes": ["瓜洲：在江苏邗江县南之运河入长江处，与镇江隔岸相对，为著名的古渡口。", "蓼：植物名，生水边，开鞭穗状小花。", "南徐：今江苏镇江市丹徒县。", "西津渡：一名金陵渡，在镇江城西蒜山下的长江边。", "北固：山名，在镇江市内长江岸上，为著名的古要塞与名胜地。"], "background": ""},
{"title": "百字令·宿汉儿村", "author": "纳兰性德", "paragraphs": "无情野火，趁西风烧遍、天涯芳草。榆塞重来冰雪里，冷入鬓丝吹老。牧马长嘶，征笳乱动，并入愁怀抱。定知今夕，庾郎瘦损多少。\t便是脑满肠肥，尚难消受，此荒烟落照。何况文园憔悴后，非复酒垆风调。回乐峰寒，受降城远，梦向家山绕。茫茫百感，凭高唯有清啸。", "topic": "秋天", "notes": ["百字令：词牌名，即念奴娇。双调一百字，上下片各十句四仄韵。", "汉儿村：在今辽宁省朝阳县境内。", "榆塞：榆关，即山海关。", "“牧马”两句：汉", "《答", "书》：“胡笳互动，牧马悲鸣。”", "庾郎：北周诗人庾信。他身经丧乱，作品饱含愁思，曾作《愁赋》。", "脑满肠肥：不操心的人，吃得饱，养得胖。", "文园：指司马相如。", "酒垆风调：据《史记·司马相如列传》，司马相如曾和妻子", "在酒店当垆卖酒。", "回乐峰：在今宁夏灵武西南。", "受降城：有三处，这里泛指边塞。"], "background": "按词中描写的是秋冬景色，且曰‘榆塞重来’，可知是指作者于康熙二十一年八，习至十二月随副都统郎谈赴梭龙时第二次至山海关，故应系于该年八、九月份。"},
{"title": "浣溪沙·露白蟾明又到秋", "author": "顾敻", "paragraphs": "露白蟾明又到秋，佳期幽会两悠悠，梦牵情役几时休？\t记得泥人微敛黛，无言斜倚小书楼，暗思前事不胜愁！", "topic": "秋天", "notes": ["蟾：月亮。传说月中有蟾蜍，故以蟾代月。", "佳期句：佳期已逝，幽会难逢，二者均茫然无望。悠悠：漫长，这里指欲相见而遥遥无期。", "泥：怜爱、留恋，作动词用。", "敛黛：皱眉。"], "background": ""},
{"title": "行香子·秋入鸣皋", "author": "许古", "paragraphs": "秋入鸣皋，爽气飘萧。挂衣冠、初脱尘劳。窗间岩岫，看尽昏朝。夜山低，晴山近，晓山高。\t细数闲来，几处村醪。醉模糊、信手挥毫。等闲陶写，问甚风骚。乐因循，能潦倒，也消摇。", "topic": "秋天", "notes": ["行香子：词牌名。双调小令，六十六字。有前段八句四平韵，后段八句三平韵；前段八句五平韵，后段八句三平韵；前段八句五平韵，后段八句四平韵三种。", "鸣皋（gāo）：山名，在今河南嵩县东北。", "挂衣冠：指辞官归隐。", "尘劳：人世间的烦劳，此指官场的应酬。", "岩岫（yán xiù）：山洞，山穴。", "醪（láo）：酒酿，此处指酿酒之处。", "陶写：即写作。", "风骚；此处指诗文的讽怨寄托，亦即其政教功利。", "乐因循：意为安于山水之乐。", "能潦倒：意为甘于淡泊寂寞。"], "background": "许古是金代中后期的谏官，明昌五年（1194）举进士，曾任左拾遗、监察御史、右司谏等职，多所补陈。后辞官归居，隐于伊阳（伊水之北）。这首词是他从官场返归山林时所作。"},
{"title": "忆王孙·番阳彭氏小楼作", "author": "姜夔", "paragraphs": "冷红叶叶下塘秋，长与行云共一舟。零落江南不自由。两绸缪，料得吟鸾夜夜愁。", "topic": "秋天", "notes": ["忆王孙：词牌名，又名《豆叶黄》《阑千万里心》。通常由31个字组成单调小令，亦有将单片重复做双调者，五平韵，句句用韵。", "冷红：指枫叶。", "绸缪：指感情缠绵深厚，不能分解。", "吟鸾：古人常以鸾凤喻夫妇。此指作者的妻子。"], "background": "宋神宗时，彭汝砺官至宝文阁直学士，他的四世孙彭大雅，公元1240年（嘉熙四年）出使北方，卒后追谥忠烈。白石回到故乡，秋日登上彭氏小楼，感叹自己飘零的身世，忆念远方的亲人，写下《忆王孙·番阳彭氏小楼作》。这首词作年不可考，从“长与行云共一舟”、“零落江南”的词意看，大约作于姜夔的中晚年。"},
{"title": "浣溪沙·波面铜花冷不收", "author": "吴文英", "paragraphs": "波面铜花冷不收。玉人垂钓理纤钩。月明池阁夜来秋。\t江燕话归成晓别，水花红减似春休。西风梧井叶先愁。", "topic": "秋天", "notes": ["浣溪沙（huàn xī shā）：浣溪沙，唐玄宗时教坊名，后用为词调。一作“纱”。 有杂言、齐言二体。", "铜花：铜镜。比喻水波清澈如镜。古代铜镜刻有花纹，故称铜花。", "纤钩：新月影，如钩，弯细的月影，约农历初二、三时的月亮。冷来秋：指比秋天还冷", "水花红：水边红蓼（liǎo），也叫水蓼，茎叶呈红色。晓：清晨时分。", "水花：荷花。春休：春天结束。", "梧井：井，即露井，无盖井。叶先愁：树叶先凋谢。梧井，取前《解连环》(暮檐凉薄)“叹梧桐未秋，露井先觉”词意，因梧桐落叶最早，由其叶落，即知秋至。"], "background": ""},
{"title": "蝶恋花·庭院碧苔红叶遍", "author": "晏几道", "paragraphs": "庭院碧苔红叶遍，金菊开时，已近重阳宴。日日露荷凋绿扇，粉塘烟水澄如练。\t试倚凉风醒酒面，雁字来时，恰向层楼见。几点护霜云影转，谁家芦管吹秋怨？", "topic": "秋天", "notes": ["蝶恋花：词牌名，双调，六十字，上下阕各五句、四仄韵。", "重阳宴：指重阳节的宴会。古时有重阳登高饮酒的风俗。", "绿扇：指荷叶。", "澄如练：形容水清澈洁白。", "见：同“现”。"], "background": ""},
{"title": "鹧鸪天·化度寺作", "author": "吴文英", "paragraphs": "池上红衣伴倚阑，栖鸦常带夕阳还。殷云度雨疏桐落，明月生凉宝扇闲。\t乡梦窄，水天宽。小窗愁黛淡秋山。吴鸿好为传归信，杨柳阊门屋数间。", "topic": "秋天", "notes": ["鹧鸪天：词牌名。据唐人诗句“春游鸡鹿塞，家在鹧鸪天”而取名。又名《思佳客》、《思越人》，", "词因有“梧桐半死清霜后”句，称《半死桐》。平韵，五十五字。上片七言四句，相当于一首七绝。下片换头两个三字句，如改为七言仄脚句，也是一首七绝。可见此调由一首七律演变而成。上片两个七字句，和换头两个三字句，前人用对偶的较多。", "化度寺：化度寺在杭州西部江涨桥附近。《杭州府志》：“化度寺在仁和县北江涨桥，原名水云，宋治平二年改。”", "红衣：莲花。", "倚阑：凭靠在栏杆上。", "殷云：浓云。", "闲：闲置。", "乡梦窄：思乡的梦太短。", "愁黛：愁眉。", "吴鸿：指苏州一带飞来的大雁。", "阊（chāng）门：苏州西门。这里指作者姬妾所居之处。"], "background": "这是一首思乡悲秋感怀之词。词人寓居杭州西部江涨桥附近的化度寺时，见秋景变化而心生感触，思念远在苏州的家人，因此写下这一首词，抒发了怅惘之情，被思念之人当为他的苏州姬妾。"},
{"title": "瑞鹤仙·秋感", "author": "吴文英", "paragraphs": "泪荷抛碎璧。正漏云筛雨，斜捎窗隙。林声怨秋色。对小山不迭，寸眉愁碧。凉欺岸帻。暮砧催、银屏翦尺。最无聊、燕去堂空，旧幕暗尘罗额。\t行客。西园有分，断柳凄花，似曾相识。西风破屐。林下路，水边石。念寒蛩残梦，归鸿心事，那听江村夜笛。看雪飞、苹底芦梢，未如鬓白。", "topic": "秋天", "notes": ["瑞鹤仙：词牌名。《清真集》、《梦窗词集》并入“高平调”，但各家句豆出入颇多。全词一百二字，前片十句七仄韵，后片十二句六仄韵。上片第二句及下片第八句为上一、下四句式。", "捎：一本作“梢”。", "迭：一本作“送”。"], "background": ""},
{"title": "贺新郎·秋晓", "author": "蒋捷", "paragraphs": "渺渺啼鸦了。亘鱼天，寒生峭屿，五湖秋晓。竹几一灯人做梦，嘶马谁行古道。起搔首、窥星多少。月有微黄篱无影，挂牵牛数朵青花小。秋太淡，添红枣。\t愁痕倚赖西风扫。被西风、翻催鬓鬒，与秋俱老。旧院隔霜帘不卷，金粉屏边醉倒。计无此、中年怀抱。万里江南吹箫恨，恨参差白雁横天杪。烟未敛，楚山杳。", "topic": "秋天", "notes": ["贺新郎：词牌名，老调始见", "词，原名《贺新凉》，又名《金缕曲》等，双调一百十六字，上下片各十句六仄韵。", "渺渺（miǎo）：微远的样子。", "啼鸦：乌鸦啼意。", "了（liǎo）：停止。", "亘（gèn）：绵亘，辽阔。", "鱼天：指水面。", "峭屿（qiào yǔ）：陡峭的岛屿。", "五湖：太湖的别名。", "窥（kuī）星多少：察看星星多少，来判断天色的迟早。因为近清晨时星渐稀少。", "青花：即牵牛花。", "愁痕：愁容。", "翻催：反而催逼。", "鬓（bìn）鬓：面额两旁的黑发。", "金粉屏：饰有彩绘的屏风。", "参（cēn）差（cī）：高低不齐。", "白雁：一种鸟，似雁而小，白色，秋天时南飞。", "天杪（miǎo）：最高处，天边。", "敛：消失。", "楚山：指太湖一带的山。", "杳（yǎo）：隐没不见。"], "background": "这首词的具体创作年代不详。但通观全篇可知，这首词作于南宋亡后。词人当时流寓苏州，隐居太湖，在秋天拂晓时分所见景物及由此兴起感慨，于是写下这首词。"},
{"title": "玉蝴蝶·秋风凄切伤离", "author": "温庭筠", "paragraphs": "秋风凄切伤离，行客未归时。塞外草先衰，江南雁到迟。\t芙蓉凋嫩脸，杨柳堕新眉。摇落使人悲，断肠谁得知。", "topic": "秋天", "notes": ["玉胡蝶：原为唐曲，后用为词牌名。有小令和长调两格。小令最早见于《花间集》，即此词。《金奁集》入“仙吕调”，四十一字，前阕四句四平韵，后阕四句三平韵。", "行客：指出行、客居的人。古人常因求学、经商或赴职所而别离故土，客居他乡。", "塞外：边塞之外，泛指中国北边地区。唐时的北方边界，大枯在今外长城一带，地处内蒙古高原、黄土高原地区。因地势与纬度均高于中原，故无霜期很短，冬季漫长，中原地区尚在粮丰果熟的中秋，塞外已是漫天飘雪的严冬了。此句意谓因塞外秋季早至，故草木先于中原地区枯败。", "雁：此处暗喻行客书信，一语双关。", "芙蓉，荷花的别称。凋，一作“雕”。脸，一作“叶”。", "杨柳，指柳叶。", "摇落：凋残，零落。", "肠断：形容极度思念或悲痛。"], "background": "晚唐时期战乱不断，思妇征夫的相思成为重要的文学题材。此词即为作者代闺中思妇抒写其对塞外征夫的相思之情。其具体创作时间未得确证。"},
{"title": "忆秦娥·季温老友归樵阳人来闲书因以为寄", "author": "孙道绚", "paragraphs": "秋寂寞。秋风夜雨伤离索。伤离索。老怀无奈，泪珠零落。\t故人一去无期约。尺书忽寄西飞鹤。西飞鹤。故人何在，水村山郭。", "topic": "秋天", "notes": ["离索：“离群索居”的略语。即离开同伴而孤独地生活。", "老怀：老来情怀。", "无奈：无可奈何。", "零落：不断地下落。", "故人：老朋友。", "无期约：没有一定的约会期。", "尺书：指书信。古人在帛上书写，通常一尺，故称。", "山郭：山傍。"], "background": "这首词是作者晚年在一个秋天所作，具体创作时间不详。词前的小序交待了写词的过程：“季温老友归樵阳，人来闲书，因以为寄。”作者独居寂寞，忽然接到久无音讯的老友季温来信，触发情怀而创作了此词。"},
{"title": "点绛唇·庚午重九再用前韵", "author": "苏轼", "paragraphs": "不用悲秋，今年身健还高宴。江村海甸。总作空花观。\t尚想横汾，兰菊纷相半。楼船远。白雪飞乱。空有年年雁。", "topic": "秋天", "notes": ["点绛唇：词牌名，此调因", "《咏自人春游》诗中有“白雪凝琼貌，明珠点绛唇”句而取名。", "庚午重九：即元祐五年（1090）九月初九。用前韵：指用《己巳重九和苏坚》一词的韵脚。", "悲愁：悲叹秋天来临。", "《九日蓝田崔氏庄》：“老去悲秋强自宽羽年此会知谁健。”", "海甸：近海地区。南齐孔德璋（稚珐）《北山移文》：“张英风于海甸，驰妙誉于浙右。”此处指郊外。", "空花：即空华。虚幻之花，比喻妄念。《圆觉经》：“譬彼病目，见空中华及第二月”又“此无名扬，非实有体，如梦中人，梦时非无，及至于醒，了无所得，如众空华，灭于虚空，不可言说。”", "横汾：汉武帝", "《秋风辞》：“秋风起兮白云飞，草木黄落兮雁南归。兰有秀兮菊有芳，怀佳人兮不能忘。泛楼船兮济汾河，横中流兮扬素波。萧鼓鸣兮发棹歌，欢乐极兮哀情多，少壮几时兮奈老何。”此词的后半阕的“横汾”、“兰菊”、“楼船”、“雁”等，均为汉武帝《秋风辞》所有。“横汾”取“济汾河，横中流”之意。", "白雪：此指白色的浪花。别本作“白云”。"], "background": "元祐五年（1090）重九日作，苏轼任杭州太守期间，结识了不少新朋友，其中一个叫苏坚，字伯固，泉州人。苏试治理西湖，他出力很大。两人情谊甚笃，唱和颇多。元祐四年（1089）重九苏坚作有《点绛唇》词，苏轼和有《己巳重九和苏坚》，元祐五年又用元祐四年韵脚和了这首词。"},
{"title": "齐天乐·绿芜凋尽台城路", "author": "周邦彦", "paragraphs": "绿芜凋尽台城路，殊乡又逢秋晚。暮雨生寒，鸣蛩劝织，深阁时闻裁剪。云窗静掩。叹重拂罗裀，顿疏花簟。尚有綀囊，露萤清夜照书卷。\t荆江留滞最久，故人相望处，离思何限。渭水西风，长安乱叶，空忆诗情宛转，凭高眺远。正玉液新篘，蟹螯初荐。醉倒山翁，但愁斜照敛。", "topic": "秋天", "notes": ["齐天乐，词牌名。又名“台城路”、“五福降中天”、“如此江山”。《清真集》、《白石道人歌曲》、《梦窗词集》并入“正宫”（即“黄钟宫”）。兹以姜词为准，一百二字，前后片各六仄韵。前片第七句、后片第八句第一字是领格，例用去声。亦有前后片首句有不用韵者。", "绿芜（lǜwú）：长得多而乱的杂草。", "《东南型一百韵》诗：“孤城覆绿芜”。", "台城：旧城名。本三国吴后苑城，晋成帝释改建为建康宫，为东晋和南朝的宫省所在，所谓禁城，亦称台城。故址在进南京玄武湖侧。宋洪迈《容斋随笔·续笔五》：“晋、宋健谓朝廷禁近为台，故称禁城为台城。”此处用以代指金陵古城（即今南京市）。", "殊乡（shū）：异乡、他乡。", "秋晚：深秋。", "暮雨：傍晚的雨。", "鸣蛩（qióng）劝织：蟋蟀的名声就像紧促的织布声。蛩：蟋蟀，以其声响织布机响，又名促织。唐", "《杂怨》诗：“暗蛩有虚织。”", "花簟（diàn）：织有花纹图案的竹凉席。", "綀（shù）囊：粗丝织品做的袋子。", "留滞：搁置；阻塞。", "篘（chōu）：漉酒竹器，亦可作动词。", "蟹螯（xiè áo）：螃蟹变形的第一对脚。状似钳，用以取食或自卫。荐：进，进献。指把蟹端上筵席来下酒。", "山翁：山翁指山简，晋代竹林七贤之一的山涛之幼子，曾镇守荆襄，有政绩，好饮酒，每饮必醉。", "斜照敛：指太阳落山。敛，收，指太阳隐没到地平线下。"], "background": "这首词当是作于绍圣二年（1095年），时周邦彦40岁。周邦彦于元祐八年（1093）三十八岁时遭到流放，被调知溧水县。词人滞留金陵时，因为郁郁不得志感慨之下作下此词。"},
{"title": "采桑子·辘轳金井梧桐晚", "author": "李煜", "paragraphs": "辘轳金井梧桐晚，几树惊秋。昼雨新愁，百尺虾须在玉钩。\t琼窗春断双蛾皱，回首边头。欲寄鳞游，九曲寒波不泝流。", "topic": "秋天", "notes": ["此词调名于《草堂诗余》、《花间集补》中作《丑奴儿令》，《类编草堂诗余》中注曰：“一名《罗敷令》，一名《采桑子》。”《类编草堂诗余》、《花草粹编》、《啸余谱》中均有题作“秋怨”。从词意看，当属", "中期的作品。", "辘轳（lùlú）：一种安在井上绞起汲水斗的器具，亦即汲取井水用的滑车。金井：井栏上有雕饰的井，这里指宫廷园林中的井。梧桐：一种落叶乔木，叶柄长，叶大，质地轻而韧。古代诗人常用梧桐金井说明时已至晚秋。", "几树：多少的树。树，这里指梧桐树。惊秋，有二种理解，一说吃惊秋天的到来，二说秋风惊动了梧桐树。两种理解尽管语意角度不同，但均可通。", "昼雨：指白天下的雨。昼，白天。新愁：指悲秋之愁。", "百尺：这里为约指，极言其长。虾须：因帘子的表状像虾的触须，所以用“虾须”作为帘子的别称。《类编草堂诗余》注中云：“虾须，帘也。”唐代陆畅《帘》诗中有句“劳将素手卷虾须，琼室流光更缀珠。”用法同。玉钩：玉制的钩子。这句话是说长长的帘子挂在玉钩上。", "琼窗：雕饰精美而华丽的窗。春断：这里指情意断绝，即男女相爱之情断绝。春，指男女相爱之情。双蛾：《花草粹编》、《花间集补》等本中均作“双娥”。即指美女的两眉。蛾，蛾眉，指妇女长而美的眉。皱：起皱纹，指皱眉。", "回首：回望。边头：指偏僻而遥远的地方。", "欲：想要。寄：寄托。鳞游：游鱼，这里借指书信。", "九曲：萧本二主词中“曲”作“月”。九曲，形容黄河河道的迂回曲折，这里代指黄河。九，泛指多数。遂以九曲代指黄河。泝（sù）流：倒流。泝，同“溯”，逆流而上。"], "background": "此词当作于开宝六年，宋太祖任命李煜的弟弟从善为泰宁军节度使，并留在京师。李煜请求宋太祖让从善回国，未获允许，作登高文，哀念不已。据说李煜非常想念他，常常痛哭，这首词是从善入宋后未归，李煜为思念他而作的。"},
{"title": "清平乐·凄凄切切", "author": "纳兰性德", "paragraphs": "凄凄切切，惨淡黄花节。梦里砧声浑未歇，那更乱蛩悲咽。\t尘生燕子空楼，抛残弦索床头。一样晓风残月，而今触绪添愁。", "topic": "秋天", "notes": ["切切：哀怨、忧伤貌。", "黄花节：指重阳节。黄花，菊花。", "砧（zhēn）声：捣衣声。", "蛩（qióng）：指蟋蟀。悲咽：悲伤呜咽", "弦索：弦乐器上的弦，指弦乐器。", "触绪：触动心绪。"], "background": "康熙十五年（公元1676年），纳兰性德再次参加进士考试，并获得了二甲第七名的成绩，康熙皇帝授予他三等侍卫的官职，词人作品此首词正是创作于作者任职御前侍卫的第二年。同时，这首词也是作者在重阳佳节为感爱妻之逝而作，为悼亡词。"},
{"title": "齐天乐·与冯深居登禹陵", "author": "吴文英", "paragraphs": "三千年事残鸦外，无言倦凭秋树。逝水移川，高陵变谷，那识当时神禹。幽云怪雨。翠萍湿空梁，夜深飞去。雁起青天，数行书似旧藏处。\t寂寥西窗久坐，故人悭会遇，同翦灯语。积藓残碑，零圭断璧，重拂人间尘土。霜红罢舞。漫山色青青，雾朝烟暮。岸锁春船，画旗喧赛鼓。", "topic": "秋天", "notes": ["齐天乐：词牌名。又名“台城路”、“五福降中天”、“如此江山”。《清真集》、《白石道人歌曲》、《梦窗词集》并入“正宫”（即“黄钟宫”）。兹以姜词为准，一百二字，前后片各六仄韵。前片第七句、后片第八句第一字是领格，例用去声。亦有前后片首句有不用韵者。", "冯深居：字可迁，号深居，江西都昌人。淳桔元年（1241）进士，与词人有交往。", "禹陵（líng）：传为夏禹的陵墓。在浙江绍兴市东南，背负会稽山。", "三千年事：夏禹在位是公元前2140年，至", "在世之年1250年，约为3390年，故曰三千年事。", "高陵变谷：高山变为低谷。比喻世事沧桑，变化无常。", "幽云怪雨：谓风雨之不同寻常。", "梁：当为禹庙之梅粱。据嘉泰《会稽志》卷六：梁时修禹庙，“唯欠一梁，俄风雨大至．湖中得一木．取以来梁，即‘梅梁’也。夜或大雷雨。梁辄失去，比复归，水草被其上．人以为神．縻以大铁绳．然犹时一失之”。", "旧藏（cáng）处：指大禹治水后藏书之处。《大明一统志·绍兴府志》：“石匮山，在府城东南一十五里，山形如匮。相传禹治水毕，藏书于此”。", "寂寥（jì liáo）：寂寞寥落．指人生亦指心境。", "悭（qiān）：稀少。", "翦灯：剪去油灯烧残的灯芯，使灯焰明亮。", "积藓（xiǎn）残碑：长满苔藓的断残古碑。", "零圭（guī）断璧：指禹庙发现的古文物。《大明一统志·绍兴府志》： “宋绍兴间，庙前一夕忽光焰闪烁，即其处剧之，得古硅璧佩环，藏于庙”。", "赛鼓：祭神赛会的鼓乐声。此指祭祀夏禹的盛会。"], "background": "理宗淳祐元年（1241）秋，词人与好友冯深居登上禹陵，感慨圣皇夏禹的丰功伟业，想到如今颓废的天下大势，有感而发，写下了这首词。"},
{"title": "踏莎行·庚戌中秋后二夕带湖篆冈小酌", "author": "辛弃疾", "paragraphs": "夜月楼台，秋香院宇。笑吟吟地人来去。是谁秋到便凄凉？当年宋玉悲如许。\t随分杯盘，等闲歌舞。问他有甚堪悲处？思量却也有悲时，重阳节近多风雨。", "topic": "秋天", "notes": ["踏莎行：词牌名。节选自《淮海词》。《踏莎行》又名《柳长春》《喜朝天》等。双调五十八字，仄韵。又有《转调踏莎行》，双调六十四字或六十六字，仄韵。", "篆（zhuàn）冈：地名，在带湖旁。", "宋玉：战国时楚国的著名诗人，", "的学生，其代表作《九辩》有句云：“悲哉秋之为气也，萧瑟兮，草木摇落而变衰。”", "如许：如此。", "随分：随意，任意。", "等闲：平常，普通。", "甚堪：什么可以。", "思量：细细想想。"], "background": "淳熙八年（1181年）冬，辛弃疾因受到弹劾而被免职，归居上饶。此后二十年间，他大部分时间都在乡间闲居，此词便是作于其间。南宋光宗绍熙元年（1190年），辛弃疾在上饶的带湖别墅篆冈喝酒赏月，成此佳作。"},
{"title": "谒金门·秋夜", "author": "苏轼", "paragraphs": "秋帷里。长漏伴人无寐。低玉枕凉轻绣被。一番秋气味。\t晓色又侵窗纸。窗外鸡声初起。声断几声还到耳。已明声未已。", "topic": "秋天", "notes": ["谒金门：词牌名。唐教坊曲名，后用为词调。又名《不怕醉》、《出塞》。", "帷：帐子。", "漏：古代计时的工具，用壶滴水的方法计算。这里代指时间。", "玉枕：陶瓷枕，以示华贵之用物。绣被：指绸缎一类的被子，富贵人家的征示。", "已：前“已”，已经。末“已”，停止。"], "background": "此词作于宋神宗熙宁六年（1073年）秋。是时，苏轼在杭州通守任上。常与朋友游西湖、孤山，登柏山、竹阁，常遇少妇慕名求词，苏轼作词以赠之，此词就是其一。"},
{"title": "关河令·秋阴时晴渐向暝", "author": "周邦彦", "paragraphs": "秋阴时晴渐向暝，变一庭凄冷。伫听寒声，云深无雁影。\t更深人去寂静，但照壁孤灯相映。酒已都醒，如何消夜永！", "topic": "秋天", "notes": ["关河令：《片玉词》“关河令”下注：“《清真集》不载，时刻‘清商怨’。”清商怨，源于古乐府，曲调哀婉。", "曾以此曲填写思乡之作，首句是“关河愁思望处满”。", "遂取“关河”二字，命名为“关河令”，隐寓着羁旅思家之意。自此，调名、乐曲跟曲词切合一致了。", "时：片时、偶尔的意思，晴：一作“作”，暝：黄昏。", "伫听：久久地站着倾听。伫，久立而等待。寒声：即秋声，指秋天的风声、雨声、虫鸟哀鸣声等。此处是指雁的鸣叫声。", "照壁：古时筑于寺庙、广宅前的墙屏。与正门相对，作遮蔽、装饰之用，多饰有图案、文字。亦谓影壁，指大门内或屏门内做屏蔽的墙壁。也有木制的，下有底座，可以移动，又称照壁、照墙。", "消夜永：度过漫漫长夜。夜永，犹言长夜。"], "background": ""},
{"title": "疏帘淡月·寓桂枝香秋思", "author": "张辑", "paragraphs": "梧桐雨细。渐滴作秋声，被风惊碎。润逼衣篝，线袅蕙炉沈水。悠悠岁月天涯醉。一分秋、一分憔悴。紫箫吟断，素笺恨切，夜寒鸿起。\t又何苦、凄凉客里。负草堂春绿，竹溪空翠。落叶西风，吹老几番尘世。从前谙尽江湖味。听商歌、归兴千里。露侵宿酒，疏帘淡月，照人无寐。", "topic": "秋天", "notes": ["衣篝：薰衣用的竹笼。", "蕙炉：香炉。", "谙：熟悉，知道。", "商歌：悲凉低沉的歌。"], "background": ""},
{"title": "玉楼春·和吴见山韵", "author": "吴文英", "paragraphs": "阑干独倚天涯客。心影暗凋风叶寂。千山秋入雨中青，一雁暮随云去急。\t霜花强弄春颜色。相吊年光浇大白。海烟沈处倒残霞，一杼鲛绡和泪织。", "topic": "秋天", "notes": ["玉楼春：据《词谱》载：“因顾敻词中有‘月照玉楼春漏促’，又有‘柳映玉楼春日晚’。五代", "词中有‘日照玉楼花似锦，楼上醉和春色寝’。又有‘春早玉楼烟雨夜’句，取为调名。”又名《木兰花》、《玉楼春令》、《西湖曲》、《呈纤手》、《东邻妙》、《春晓曲》、《惜春容》、《梦相亲》、《归风便》、《归朝欢令》、《转调木兰花》、《续渔歌》。双调，五十六字，上下片各四句三仄韵。", "和吴见山韵：和韵，是用他人诗词所用的韵而作诗词。分用韵、依韵、次韵三种。", "说：“古时有唱有和，有杂拟追和之类，而无和韵者。唐始有用韵，谓同用此韵；后有依韵，然不以次；后有次韵。自元（稹）、白(居易)至皮（日休）、陆（龟蒙），其体乃全。”吴见山，梦窗词友，常有唱酬相和。《梦窗词》中，题其名的即有六首，而和词或用其原韵而作的竟有五首之多。", "大白：酒名。"], "background": ""},
{"title": "扫花游·秋声", "author": "王沂孙", "paragraphs": "商飙乍发，渐淅淅初闻，萧萧还住。顿惊倦旅。背青灯吊影，起吟愁赋。断续无凭，试立荒庭听取。在何许？但落叶满阶，惟有高树。\t迢递归梦阻。正老耳难禁，病怀凄楚。故山院宇。想边鸿孤唳，砌蛩私语。数点相和，更著芭蕉细雨。避无处。这闲愁，夜深尤苦。", "topic": "秋天", "notes": ["秋声：时至秋日，西风起，草木凋零，多肃杀之声，曰秋声。", "商飙（biāo）：指秋风 。古人把五音与四季相配。商音配秋。商音凄厉。与秋无肃杀之气相应。因以商指秋季。", "淅淅：象声词，形容风声。", "倦旅：指倦于行旅的人。", "青灯：光线青荧的油灯，借指孤寂、清苦的生活。", "吊影：对影自伤。极言孤独。愁赋：度郎先自吟愁赋，凄凄更闻私语 。", "断续：意指风声不定时断时续。无凭，无准或不定之义。何许：何处。但：只，只有。", "迢（tiáo）递：遥远的样子。", "老耳难禁：老来不堪的取凄凉的秋声。", "边鸿：边塞的鸿雁。孤唳：指鸿雁孤鸣。砌蛩：台阶下的蟋蟀。", "数点：指雨滴。更著：更加上。"], "background": "至元二十八年（1291），元朝诏告天下寻访隐居埋名的人士，征辟任用南士，并责成各级官府严加督视。宋亡后一直隐居会稽的王沂孙在这一年被强征而起，出任庆元路学正。这一首《扫花游·秋声》，便是他出任庆元任上，日夜思念故乡并渴盼早日归家的心迹流露。"},
{"title": "鹧鸪天·枫落河梁野水秋", "author": "苏庠", "paragraphs": "枫落河梁野水秋。淡烟衰草接郊丘。醉眠小坞黄茅店，梦倚高城赤叶楼。\t天杳杳，路悠悠。钿筝歌扇等闲休。灞桥杨柳年年恨，鸳浦芙蓉叶叶愁。", "topic": "秋天", "notes": ["河梁：桥梁。", "杳杳：深远幽暗貌。", "悠悠：遥远。", "钿筝：嵌金为饰之筝。", "芙蕖：荷花的别名。"], "background": "徽宗大观、政和之际，苏庠曾依苏固与徐俯、洪刍等结诗社于江西，在澧阳（今湖南澧县）筑别墅以供游憩。高宗绍兴年间，苏庠与徐俯同被皇帝征召，只有他自己不前往朝廷，隐居直到去世。此诗写于作者推掉皇帝征召游玩于山水，路过一小山村时见景思情有感而发。"},
{"title": "小桃红·杂咏", "author": "盍西村", "paragraphs": "绿杨堤畔蓼花洲，可爱溪山秀，烟水茫茫晚凉后。捕鱼舟，冲开万顷玻璃皱。乱云不收，残霞妆就，一片洞庭秋。", "topic": "秋天", "notes": ["洲：水中的陆地。", "“烟水”句：傍晚以后，天气宜人。水面上烟雾笼罩，一片迷茫。", "玻璃皱：比喻水浪。", "秋：指秋色。"], "background": ""},
{"title": "踏莎行·秋入云山", "author": "张抡", "paragraphs": "秋入云山，物情潇洒。百般景物堪图画。丹枫万叶碧云边，黄花千点幽岩下。\t已喜佳辰，更怜清夜。一轮明月林梢挂。松醪常与野人期，忘形共说清闲话。", "topic": "秋天", "notes": ["秋入:进入秋天。", "丹枫：亦称霜叶、红叶。", "万叶：极言枫叶之多。", "碧云：青白色的云气。", "黄花千点：无数的菊花。", "幽岩下：山岩深幽之处。", "林梢挂：挂在树梢上。", "松醪：是松膏酿制的酒。", "常与：点明了兴趣所在，乐此不疲。", "野人：山野之人。", "期：约会之意。", "忘形：便是隐士悠然自得、不拘形迹的写照。", "共说清闲话:一起谈天说地。"], "background": "张抡，宋高宗年间独自登高秋游，赏万山秋景，有感而发，故作此词。"},
{"title": "沁园春·张路分秋阅", "author": "刘过", "paragraphs": "万马不嘶，一声寒角，令行柳营。见秋原如掌，枪刀突出，星驰铁骑，阵势纵横。人在油幢，戎韬总制，羽扇从容裘带轻。君知否，是山西将种，曾系诗盟。\t龙蛇纸上飞腾。看落笔四筵风雨惊。便尘沙出塞，封侯万里，印金如斗，未惬平生。拂拭腰间，吹毛剑在，不斩楼兰心不平。归来晚，听随军鼓吹，已带边声。", "topic": "秋天", "notes": ["沁园春：词牌名，又名《寿星明》、《洞庭春色》等。双调一百十四字，平韵。", "星驰铁骑：带甲的骑兵如流星般奔驰。", "油幢：油布制的帐幕。", "戎韬总制：以兵法来部勒指挥。戎韬指的是兵法。", "羽扇从容：三国时", "常手执羽扇，从容指挥战事。裘带轻：即轻裘缓带，用羊祜故事。羊祜是西晋人，出镇襄阳十年间，他轻裘缓带，身不披甲，有儒将之风。", "山西将种：古人认为华山以西之地是出将才的地方。", "龙蛇：喻书法。", "惬：满足，畅快。", "吹毛剑：指锋利的剑。", "楼兰：此指金统治者。"], "background": "古代军队时常在秋天进行演习，并有长官进行检阅，所以叫“秋阅”。词题中的“张路分”，姓张，官居路分都监，生平不详。路分都监是宋代路级的军事长官。作者看到爱国将领张路分“秋阅”的情景，有感而发写下该词。"},
{"title": "定风波·江水沉沉帆影过", "author": "阎选", "paragraphs": "江水沉沉帆影过，游鱼到晚透寒波。渡口双双飞白鸟，烟袅，芦花深处隐渔歌。\t扁舟短棹归兰浦，人去，萧萧竹径透青莎。深夜无风新雨歇，凉月，露迎珠颗入圆荷。", "topic": "秋天", "notes": ["沉沉：深沉。", "烟袅：云烟缭绕。袅，形容烟之状态。", "棹：船桨。", "兰浦：意思是长着兰草的水边。浦，水边。", "萧萧：风声，也指草木摇落声。", "莎（suō）：莎草，多年生草本植物，地下的块根称“香附子”，可入药。"], "background": ""},
{"title": "谒金门·秋感", "author": "苏轼", "paragraphs": "今夜雨。断送一年残暑。坐听潮声来别浦。明朝何处去。\t孤负金尊绿醑。来岁今宵圆否。酒醒梦回愁几许。夜阑还独语。", "topic": "秋天", "notes": ["谒金门：词牌名。", "断送：犹言结束。残暑：暑天最后最热的时间在三伏，俗称“秋老虎”。", "浦：水滨，这里指钱塘江边。", "孤负：对不起。金尊：金杯。绿醑（xǔ）：绿色美酒。唐太宗《春日玄武门宴群臣》：清尊浮绿醑，雅曲韵朱弦。", "来岁：明年。圆：团圆，引伸为相聚。", "回：醒来。几许：多少。", "夜阑：夜深。"], "background": "此词约作于宋神宗熙宁六年（1073年）七月十五日，是时，东坡在杭州通守任上。与《谒金门·秋夜》一样，此词系东坡与人酬赠之作。"},
{"title": "长相思·去年秋", "author": "佚名", "paragraphs": "去年秋，今年秋，湖上人家乐复忧。西湖依旧流。\t吴循州，贾循州，十五年前一转头。人生放下休。", "topic": "秋天", "notes": ["湖上人家：特指贾似道。他在西湖葛岭筑有“半闲堂”。", "乐复忧：指乐忧相继，言其祸福无常。", "吴循州：指吴潜。", "贾循州：指贾似道。"], "background": "据《东南纪闻》卷一载，这首词题于“（贾）似道贬时”，当在公元1275年（宋恭帝德祐元年）。作者因有感于左右两丞相吴潜、贾似道先后贬循州（今广东龙川）事而作此词。"},
{"title": "眼儿媚·萋萋芳草小楼西", "author": "刘基", "paragraphs": "萋萋芳草小楼西，云压雁声低。两行疏柳，一丝残照，万点鸦栖。\t春山碧树秋重绿，人在武陵溪。无情明月，有情归梦，同到幽闺。", "topic": "秋天", "notes": ["眼儿媚：词牌名，又名“秋波媚”、“小阑干”、“东风寒”等，双调，正体为四十八字，上片五句三平韵，下片五句两平韵。", "武陵溪：借", "《桃花源记》武陵渔人进入桃花源事，借指爱人在远方。", "《凤凰台上忆吹箫·香冷金猊》：“念武陵人远，烟锁秦楼。”", "归梦：指远游人惦念家里的魂梦。"], "background": ""},
{"title": "金缕曲·癸酉秋出都述怀有赋", "author": "龚自珍", "paragraphs": "我又南行矣！笑今年、鸾飘凤泊，情怀何似？纵使文章惊海内，纸上苍生而已。似春水、干卿何事？暮雨忽来鸿雁杳，莽关山、一派秋声里。催客去，去如水。\t华年心绪从头理，也何聊、看潮走马，广陵吴市。愿得黄金三百万，交尽美人名士。更结尽、燕邯侠子。来岁长安春事早，劝杏花、断莫相思死。木叶怨，罢论起。", "topic": "秋天", "notes": ["金缕曲：词牌名，又名“贺新郎”﹑“乳燕飞”，一百十六字，上片五十七字，下片五十九字，各十句六仄韵。癸酉（yǒu）：嘉庆十八年（1813年）。", "鸾飘凤泊：比喻英俊之士落魄沉沦，亦兼寓夫妻离别意。", "卿：你，作者自谓。", "聊：愿意。 广陵：今江苏扬州。 吴市：指苏州，与扬州皆当时吴越之地的大都会。", "燕邯侠子：燕指古燕国，国都为蓟（北京），邯指河北邯郸，为赵国都城。古称燕赵之地多侠士，故以为代称。", "断莫：千万不要。", "木叶：树叶。木叶怨似指飘落之悲。", "罢论：罢休之论，指作罢了经国纬世之志，誓愿隐逸草野江湖。"], "background": "这首词作于嘉庆十八年（1813年），这年四月，作者由徽州父亲府署赴北京应顺天乡试，未第，却赶上了林清等领导的天理教起义军攻打皇宫的重大事变。七月，其新结缡的妻子段美贞病殁。数月间接连遇见人生两大挫折，龚自珍心中自不能免苍凉之感，悲慨之情，作此词述怀。"},
{"title": "鹧鸪天·寒日萧萧上锁窗", "author": "李清照", "paragraphs": "寒日萧萧上锁窗，梧桐应恨夜来霜。酒阑更喜团茶苦，梦断偏宜瑞脑香。\t秋已尽，日犹长，仲宣怀远更凄凉。不如随分尊前醉，莫负东篱菊蕊黄。", "topic": "秋天", "notes": ["萧萧：凄清冷落的样子。原为象声词，如风声、雨声、草木摇落声、马蹄声。《诗经·小雅·车攻》有“萧萧马鸣”，《楚辞·九怀·蓄英》有“秋风兮萧萧”，《史记·刺客列传》有“风萧萧兮易水寒”。琐窗：镂刻连锁纹饰之窗户。多本兮锁窗，当以琐窗为胜。", "酒阑：酒尽，酒酣。阑：残，尽，晚。", "《史记·高祖本纪》有“酒阑”，裴骃集解曰“阑，言希也。谓饮酒者半罢半在，谓之阑。”文选·", "《宋孝武宣贵妃诔》有“白露凝兮岁将阑”，李善注曰“阑，犹晚也”。团茶：团片状之茶饼，饮用时则碾碎之。宋代有龙团、凤团、小龙团等多种品种，比较名贵。", "《归田录》卷二：“茶之品，莫贵于龙凤，谓之团茶，凡八饼重一斤。”", "瑞脑：即龙涎香，一名龙脑香。", "仲宣：王粲，字仲宣，汉末文学家，“建安七子”之一。其《登楼赋》抒写去国怀乡之思，驰名文坛。", "随分：随便，随意。尊前：指宴席上。尊：同“樽”。", "东篱菊蕊黄：化用陶渊明《饮酒二十首》的“采菊东篱下”句。"], "background": "此词写作时间尚有争议，有人认为是李清照“晚年流寓越中所作”，当时赵明诚已去世，“茶苦”和“梦断”二语是暗寓作者的亡夫之痛。"},
{"title": "声声慢·秋声", "author": "蒋捷", "paragraphs": "黄花深巷，红叶低窗，凄凉一片秋声。豆雨声来，中间夹带风声。疏疏二十五点，丽谯门、不锁更声。故人远，问谁摇玉佩，檐底铃声？\t彩角声吹月堕，渐连营马动，四起笳声。闪烁邻灯，灯前尚有砧声。知他诉愁到晓，碎哝哝、多少蛩声！诉未了，把一半、分与雁声。", "topic": "秋天", "notes": [], "background": "在深秋时节，词人凭窗聆听着连绵不断的秋雨声，不禁引起心中阵阵凄凉，于是写下这首词。"},
{"title": "眼儿媚·萧萧江上荻花秋", "author": "贺铸", "paragraphs": "萧萧江上荻花秋，做弄许多愁。半竿落日，两行新雁，一叶扁舟。\t惜分长怕君先去，直待醉时休。今宵眼底，明朝心上，后日眉头。", "topic": "秋天", "notes": ["萧萧：形容风声。", "做弄：犹捉弄。"], "background": ""},
{"title": "浣溪沙·山色横侵蘸晕霞", "author": "苏轼", "paragraphs": "山色横侵蘸晕霞，湘川风静吐寒花。远林屋散尚啼鸦。\t梦到故园多少路，酒醒南望隔天涯。月明千里照平沙。", "topic": "秋天", "notes": ["浣溪沙：唐教坊曲名，后用为词牌。“沙”或作“纱”，亦作“浣纱溪”。双调42字，分平韵、仄韵两体。上片三句皆平韵，下片三句有两句平韵。", "横侵：纵横扩展。", "蘸（zhàn）：原意为把物件浸入水中，引申为以液体沾染他物。", "晕霞：指太阳光线经云层中冰晶的折射而形成的光象，这里指晚霞。", "湘川：不是指湖南湘水，这里指湖北古荆州地区。", "寒花：寒冷天气开的花，但在古代诗词中多指菊花。", "尚：尚有。", "南望：是词句的省略语，指", "从荆州遥望故乡四川眉山，其方向应在西南。", "平沙：广阔的沙原，当指荆州长江江岸的辽阔沙原。"], "background": "宋仁宗嘉祐四年（1059年）十一月，苏轼自故乡四川眉山沿长江返回朝堂，行舟至荆州之前，见长江两岸深秋季节的景色写下该词。"},
{"title": "渔歌子·荻花秋", "author": "李珣", "paragraphs": "荻花秋，潇湘夜，橘洲佳景如屏画。碧烟中，明月下，小艇垂纶初罢。\t水为乡，篷作舍，鱼羹稻饭常餐也。酒盈杯，书满架，名利不将心挂。", "topic": "秋天", "notes": ["渔歌子：词牌名。原唐教坊曲名，后成为词牌名。单调二十七字，四平韵。中间三言两句，例用对偶。", "荻（dí）：多年生草本植物，秋季抽生草黄色扇形圆锥淼序，生长在路边和水旁。", "潇湘：两水名，今湖南境内。《山海经》：“潇水，源出九巅山，湘水，源出海阳山。至零陵合流而于洞庭也。”", "橘洲：在长沙市境内湘江中，又名下洲，旧时多橘，故又称“橘子洲”。《水经注·湘水》：“湘水又北经南津城西，西对橘洲。”", "垂纶（lún）：垂钓。纶，较粗的丝线，常指钓鱼线。", "篷：船帆，此处代指船。", "“名利”句：即心不将名利牵挂。"], "background": "前蜀灭亡后，词人不仕后蜀，对前蜀怀有故国之思，便向往江湖。李珣从蜀中乘船沿长江东下，在湖南、湖北一带过了一段时期的隐居生活，然后溯湘水而上，后来他在岭南生活了较长时期。词人乘船经过湖南、湖北一带，创作了大量描写隐逸生活的词作，这首《渔歌子》便是其中之一。"},
{"title": "谢新恩·冉冉秋光留不住", "author": "李煜", "paragraphs": "冉冉秋光留不住，满阶红叶暮。\t又是过重阳，台榭登临处，茱萸香坠。\t紫菊气，飘庭户，晚烟笼细雨。\t雍雍新雁咽寒声，愁恨年年长相似。", "topic": "秋天", "notes": [], "background": ""},
{"title": "采莲子·船动湖光滟滟秋", "author": "皇甫松", "paragraphs": "船动湖光滟滟秋，贪看年少信船流。\t无端隔水抛莲子，遥被人知半日羞。", "topic": "秋天", "notes": ["滟滟：水面闪光的样子。", "举棹：括号里的“举棹”“年少”，均为和声。", "年少：指少年男子。信船流：任船随波逐流。", "无端：无故，没来由。"], "background": ""},
{"title": "更漏子·本意", "author": "王夫之", "paragraphs": "斜月横，疏星炯。不道秋宵真永。声缓缓，滴泠泠。双眸未易扃。\t霜叶坠，幽虫絮，薄酒何曾得醉。天下事，少年心。分明点点深。", "topic": "秋天", "notes": ["炯（jiǒng）：明亮。", "永：漫长。", "滴泠（líng）泠（líng）：指漏壶滴水之声。", "扃（jiōng）：门上钮环，喻闭门，引申为闭眼。", "幽：阴暗的角落", "絮（xù）：鸣叫", "薄：少许。"], "background": "明朝灭亡后，王夫之在家乡衡阳抗击清兵，失败后，隐居石船山，从事思想方面的著述。晚年身体不好，生活又贫困，写作时连纸笔都要靠朋友周济。王夫之每天都在写文章，以至于磨砚，提笔都觉得费力。王夫之感到报国无门，内心感觉非常悲凉，便把内心的苦楚宣泄在文学作品中。"},
{"title": "长相思·云一涡", "author": "李煜", "paragraphs": "云一緺，玉一梭，淡淡衫儿薄薄罗。轻颦双黛螺。\t秋风多，雨相和，帘外芭蕉三两窠。夜长人奈何！", "topic": "秋天", "notes": ["长相思：此词调名在曾慥《乐府雅词》中作《长相思令》。", "云：指妇女蓬卷如云的头发。", "一緺（wō）：即一束。一说緺，读为guā，意为青紫色的绶带（丝带）。这里指饰发用的紫青色丝带。元薛惠英《苏台竹枝词》中有句：“一凤髻绿如云，八字牙梳白似银。”", "玉：这里指插在女子头上的玉簪。梭：萧本二主词中误作“梳”。梭，原是织布用的梭子，这里用以比喻玉簪。", "淡淡：指衣裳的颜色轻淡。", "衫儿：古代女子穿的短袖上衣，又称衫子或半衣。", "薄薄：指衣裳的质料轻薄。", "罗：丝罗，这里指用丝罗制成的裙子（下裳），即罗裙。", "颦（pín）：皱眉。黛：古代妇女用来画眉的青黑色颜料。", "黛螺：《龙洲集》中作“翠娥”。黛螺，又名黛子螺。古代女子画眉用的螺形黛黑，亦称螺黛。因其用来画眉，所以常用以作妇女眉毛的代称。", "相：指雨声和风声，相互应和，交织一起。"], "background": "这首词应是李煜前期的作品，当时“生于深宫之中，长于妇人之手”的他，作为南唐后主，生活在奢华的宫廷之中，并没有过多的忧心事。他经常去关注宫廷之中男女之间的情感，因此词中多反映了帝王生活中宫廷歌舞宴乐的盛况和男女情爱。"},
{"title": "清平乐·候蛩凄断", "author": "张炎", "paragraphs": "候蛩凄断，人语西风岸。月落沙平江似练，望尽芦花无雁。\t暗教愁损兰成，可怜夜夜关情。只有一枝梧叶，不知多少秋声！", "topic": "秋天", "notes": ["清平乐：唐代教坊曲名，后用为词牌。又名《清平乐令》、《忆萝花》、《醉东风》等。双调四十六字。前段四句四仄韵；后段四句三平韵。又一体，前段四句四仄韵；后段四句三仄韵。", "蛩（qióng）：蟋蟀。", "练：素白未染之熟绢。", "芦花：芦絮。芦苇花轴上密生的白毛。", "愁损：愁杀。", "兰成：北周庾信的小字。", "关情：动心，牵动情怀。"], "background": "此词见于《山中白云词》卷四。原是张炎赠给他的学生陆行直（又称陆辅之）的。其时，张炎年五十三岁。"},
{"title": "戚氏·晚秋天", "author": "柳永", "paragraphs": "晚秋天，一霎微雨洒庭轩。槛菊萧疏，井梧零乱，惹残烟。凄然，望江关，飞云黯淡夕阳间。当时宋玉悲感，向此临水与登山。远道迢递，行人凄楚，倦听陇水潺湲。正蝉吟败叶，蛩响衰草，相应喧喧。\t孤馆，度日如年。风露渐变，悄悄至更阑。长天净，绛河清浅，皓月婵娟。思绵绵。夜永对景，那堪屈指，暗想从前。未名未禄，绮陌红楼，往往经岁迁延。\t帝里风光好，当年少日，暮宴朝欢。况有狂朋怪侣，遇当歌对酒竞留连。别来迅景如梭，旧游似梦，烟水程何限。念名利，憔悴长萦绊。追往事、空惨愁颜。漏箭移，稍觉轻寒。渐呜咽，画角数声残。对闲窗畔，停灯向晓，抱影无眠。", "topic": "秋天", "notes": ["戚氏：词牌名，为", "所创，长调慢词，《乐章集》收入“中吕调”。全词三叠，计212字，为北宋长调慢词之最，亦堪称柳词压轴之作。", "一霎：一阵。庭轩：庭院里有敞窗的厅阁。", "槛菊：栏杆外的菊花。井梧：井旁挺拔的梧桐古树。源自唐", "《井梧吟》：\"庭除一古桐,耸干入云中。枝迎南北鸟，叶送往来风。\"", "江关：疑即指荆门，荆门、虎牙二山（分别在今湖北省枝城市和宜昌市）夹江对峙，古称江关，战国时为楚地。", "宋玉悲感：战国·楚宋玉作《九辩》，曾以悲秋起兴，抒孤身逆旅之寂寞，发生不逢时之感慨。", "迢递：遥不可及貌。迢：高貌", "陇水：疑非河流名，实为陇头流水之意。北朝乐府有《陇头歌辞》，词曰：“陇头流水，流离山下。念吾一身，飘然旷野。”“陇头流水，鸣声呜咽。遥望秦川，心肝断绝。”", "潺湲（音婵媛）：水流貌。", "蛩（音穷）：蟋蟀也。", "更（音耕）阑：五更将近，天快要亮了。犹言夜深。", "绛河：即银河。天空称为绛霄，银河称为绛河。", "婵娟：美好貌。", "夜永：夜长也。", "绮陌红楼：犹言花街青楼。绮陌：繁华的道路。", "经岁：经年，以年为期。", "迁延：羁留也。", "帝里：京城。", "狂朋怪侣：狂放狷傲的朋友。", "竞：竞相也。", "迅景：岁月也，光阴易逝，故称。", "程：即路程。", "萦绊：犹言纠缠。", "漏箭：古时以漏壶滴水计时，漏箭移即光阴动也。", "画角：古时军用管乐器，以竹木或皮革制成，发声哀厉高亢，多用于晨昏报时或报警，因表面有彩绘，故称画角。", "停灯：即吹灭灯火。", "抱影无眠：守着自己的孤影，一夜没有睡着。"], "background": "从词中“宋玉悲感，向此临水与登山”来看，这首词当写于湖北江陵，当时柳永外放荆南，已经年过五十，只做个相当于县令的小官，心情自然十分苦闷。这种情绪在这首词里得到充分的体现。,"},
{"title": "秋波媚·七月十六日晚登高兴亭望长安南山", "author": "陆游", "paragraphs": "秋到边城角声哀，烽火照高台。悲歌击筑，凭高酹酒，此兴悠哉。\t多情谁似南山月，特地暮云开。灞桥烟柳，曲江池馆，应待人来。", "topic": "秋天", "notes": ["秋波媚：词牌名。双调四十八字，前片三平韵，后片两平韵。", "高兴亭：亭名，在南郑（今属陕西）内城西北，正对当时在金占领区的长安南山。南郑地处南宋抗金前线，当时", "在南郑任上。", "角声：行军打仗用的鼓角之声。", "烽火：古代边防措施，于高峰处建台，镇守士卒于敌炬，白昼举烟，夜间置火，警视军民作好防御和迎敌准备。后又有每日处夜放烟一炬，谓之平安火。此指报前线无事的平安烽火。高台：本处指高兴亭。", "筑：古代的一中弦乐器。", "酹（lèi）酒：把酒洒在地上的祭祀仪式。", "灞桥：在今陕西西安城东。唐人送客至此桥，折柳赠别。为唐代长安名胜。", "曲江：池名，在今陕西西安东南。为唐代以来的游览胜地。", "应：应该。人：指宋军，也包括作者。"], "background": "1172年（孝宗乾道八年），陆游四十八岁。他接受四川宣抚使王炎邀请，来到南郑，担任四川宣抚使公署干办公事兼检法官，参加了9个月的从军生活。南郑是当时抗金的前线，王炎是抗金的重要人物，主宾意气十分相投。高兴亭，在南郑内城的西北，正对南山。凭高远望，写下这首词。"},
{"title": "满庭芳·碧水惊秋", "author": "秦观", "paragraphs": "碧水惊秋，黄云凝暮，败叶零乱空阶。洞房人静，斜月照徘徊。又是重阳近也，几处处，砧杵声催。西窗下，风摇翠竹，疑是故人来。\t伤怀。增怅望，新欢易失，往事难猜。问篱边黄菊，知为谁开。谩道愁须殢酒，酒未醒、愁已先回。凭阑久，金波渐转，白露点苍苔。", "topic": "秋天", "notes": ["洞房：深邃的内室。", "砧杵（zhēn chǔ）：古代捣衣工具。砧为捣衣石，杆为捣衣棒。南朝宋", "《捣衣》诗：“搁高砧响发，楹长杵声哀。”《子夜四时歌·秋歌》：“佳人理寒服，万结砧杵劳。”", "西窗三句：西窗，唐代诗人", "《夜雨寄北》诗：“何当共剪西窗烛，却话巴山夜雨时。”疑是故人来，唐代诗人", "《竹窗闻风寄苗发", "》诗：“开门复动竹，疑是故人来。”", "问篱边二句：思念故乡。语本晋", "《饮酒》诗之五：“采菊东篱下，悠然见南山。”唐", "《秋兴八首》：“丛菊两开他日泪，扁舟一系故园心。”", "殢酒（tì）：病酒，为酒所困。此为以酒浇愁之意。作者《梦扬州》词云：“滞酒困花，十载因谁淹留。”", "金波二句：金波，月光。《汉书·礼乐志》：“月穆穆以金波。”"], "background": "秦观为官时期因政治上倾向于旧党，被目为元祐党人，绍圣后贬谪。此词一说为他被流放因思恋故国所作，另一说为他晚年谪居后而做。"},
{"title": "踏莎行·碧海无波", "author": "晏殊", "paragraphs": "碧海无波，瑶台有路。思量便合双飞去。当时轻别意中人，山长水远知何处。\t绮席凝尘，香闺掩雾。红笺小字凭谁附。高楼目尽欲黄昏，梧桐叶上萧萧雨。", "topic": "秋天", "notes": ["踏莎（suō）行：词牌名。又名“柳长春”“喜朝天”“踏雪行”等。双调五十八字，仄韵。", "碧海：传说中的海名。《海内十洲记》：“ 扶桑在东海 之东岸。岸直，陆行登岸一万里，东复有碧海。海广狭浩汗，与东海等。水既不咸苦，正作碧色，甘香味美。”", "瑶台：指传说中的神仙居处。晋王嘉《拾遗记·昆仑山》：“傍有瑶台十二，各广千步，皆五色玉为台基。”", "思量：考虑；忖度。", "意中人：心中所眷恋或属意的人。", "绮席：华丽的席具。古人称坐卧之铺垫用具为席。南朝梁", "《杂体诗·效惠休〈怨别〉》：“膏炉绝沉燎，绮席生浮埃。”", "香闺：青年女子的内室。唐", "《柳陌听早莺》诗：“乍使香闺静，偏伤远客情。”", "红笺（jiān）：红色笺纸。唐", "（wò）《偶见》诗“小叠红笺书恨字，与奴方便寄卿卿”，此化用之。附：带去。"], "background": "《踏莎行·碧海无波》当作于天圣五年（1027）作者贬知宣州途中。作者因反对张耆升任枢密使，违反了刘太后的旨意，加之在玉清宫怒以朝笏撞折侍从的门牙，被御史弹劾，以刑部侍郎贬知宣州，此词即在途中所作。"},
{"title": "浪淘沙·夜雨做成秋", "author": "纳兰性德", "paragraphs": "夜雨做成秋，恰上心头。教他珍重护风流。端的为谁添病也，更为谁羞。\t密意未曾休，密愿难酬。珠帘四卷月当楼。暗忆欢期真似梦，梦也须留。", "topic": "秋天", "notes": ["浪淘沙：唐教坊曲。", "、", "并作七言绝句体，五代时始流行长短句双调小令，又名《卖花声》。28字，前后片各四平韵，多作激越凄壮之音。", "风流：指美好动人之风韵。前蜀花蕊失人《宫词》之三十：“年初十五最风流，新赐云鬟使上头。”", "端韵：究竟、到底。", "密意：隐秘韵情意。", "珠帘四卷：谓楼阁四面韵珠帘卷起。"], "background": "康熙年间，由于对亡妻的怀念，对友人的牵绊，还有对自身现状的不满以及无能为力的无奈，都让词人感到悲哀。于是词人为了抒发自己内心的无边无际的愁绪，写下了这首《浪淘沙》。"},
{"title": "浣溪沙·荷花", "author": "苏轼", "paragraphs": "四面垂杨十里荷，问云何处最花多。画楼南畔夕阳和。\t天气乍凉人寂寞，光阴须得酒消磨。且来花里听笙歌。", "topic": "秋天", "notes": ["浣溪沙：唐教坊曲，后用为词牌名。", "问云句：袭用", "《奉酬卢给事云夫四兄〈曲江荷花行〉》诗“问言何处荚蓉多”句。下句“画楼南畔”是“何处”的回答。", "光阴句：承上句“人寂寞”，因寂寞无聊，所以要用酒消遣日子。唐人", "《样潼岁暮》诗：“美酒消磨日”、", "《退居述怀寄北京韩侍中》诗“万事消磨酒百分”。消磨：消遣，排遣。", "笙（shēng）歌：合笙之歌。"], "background": "此词作于宋哲宗元祐六年（1091年）闰八月至九月间词人初到颍州太守任上。词人当时在观赏颍州西湖的荷花，忽然感觉当官寂寞孤寥，于是作下了这首诗。"},
{"title": "鹧鸪天·寒日萧萧上琐窗", "author": "李清照", "paragraphs": "寒日萧萧上琐窗，梧桐应恨夜来霜。酒阑更喜团茶苦，梦断偏宜瑞脑香。\t秋已尽，日犹长，仲宣怀远更凄凉。不如随分尊前醉，莫负东篱菊蕊黄。", "topic": "秋天", "notes": ["萧萧：凄清冷落的样子。原为象声词，如风声、雨声、草木摇落声、马蹄声。《诗经·小雅·车攻》有“萧萧马鸣”，《楚辞·九怀·蓄英》有“秋风兮萧萧”，《史记·刺客列传》有“风萧萧兮易水寒”。琐窗：镂刻连岁纹饰之窗户。多本作岁窗，当以琐窗为胜。", "酒阑：酒尽，酒酣。阑：残，尽，晚。", "《史记·高祖本纪》有“酒阑”，裴骃集解曰“阑，言希也。谓饮酒者半罢半在，谓之阑。”文选·", "《宋孝武宣贵妃诔》有“白露凝兮岁将阑”，李善注曰“阑，犹晚也”。团茶：团片状之茶饼，饮用时则碾碎之。宋代有龙团、凤团、小龙团等多种品种，比较名贵。", "《归田录》卷二：“茶之品，莫贵于龙凤，谓之团茶，凡八饼重一斤。”", "瑞脑：即龙涎香，一名龙脑香。", "仲宣：王粲，字仲宣，汉末文学家，“建安七子”之一。其《登楼赋》抒写去国怀乡之思，驰名文坛。", "随分：随便，随意。尊前：指宴席上。尊：同“樽”。", "东篱菊蕊黄：化用陶渊明《饮酒二十首》的“采菊东篱下”句。"], "background": "这首词写秋景，寄乡愁，应是李清照晚期作品。依词中“仲宣怀远”和“莫负东篱”两句，这首词大概作于李清照南渡后不久，时间大约是公元1128年（宋高宗建炎二年），那时赵明诚正在江宁任知府。"},
{"title": "天净沙·秋", "author": "朱庭玉", "paragraphs": "庭前落尽梧桐，水边开彻芙蓉。解与诗人意同。辞柯霜叶，飞来就我题红。", "topic": "秋天", "notes": ["芙蓉：指荷花。", "辞柯：离开枝干。", "题红：在红叶上题诗。唐僖宗时，有一名宫女在红叶上写了一首诗：“流水何太急，深宫尽日闲。愍憨谢红叶，好去到人间。”树叶顺着御沟水流出宫墙。书生于祐拾到后添写道：“曾闻叶上题红怨，叶上题诗寄阿谁？”置于流水上游又流入宫中。后两人终成良缘。"], "background": ""},
{"title": "南乡子·重九涵辉楼呈徐君猷", "author": "苏轼", "paragraphs": "霜降水痕收。浅碧鳞鳞露远洲。酒力渐消风力软，飕飕。破帽多情却恋头。\t佳节若为酬。但把清尊断送秋。万事到头都是梦，休休。明日黄花蝶也愁。", "topic": "秋天", "notes": [], "background": "这首词是苏轼贬谪黄州期间，于元丰五年（1082年）重阳日郡中涵辉楼宴席上为黄州知州徐君猷而作。"},
{"title": "普天乐·秋怀", "author": "张可久", "paragraphs": "为谁忙，莫非命。西风驿马。落月书灯。青天蜀道难，红叶吴江冷。两字功名频看镜，不饶人白发星星。钓鱼子陵，思莼季鹰，笑我飘零。", "topic": "秋天", "notes": ["西风驿马：指在萧瑟西风中驱马奔忙。", "吴江：即松江，为太湖最大的支流。", "钓鱼子陵：指拒绝汉光武帝征召，隐居垂钓的严光。", "思莼季鹰:", "，字季鹰。翰因见秋风起，乃思吴中菰菜．莼羹．鲈鱼脍，曰：人生贵得适志，何能羁宦数千里以要名爵乎！遂命驾而归。"], "background": ""},
{"title": "御街行·秋日怀旧", "author": "范仲淹", "paragraphs": "纷纷坠叶飘香砌。夜寂静，寒声碎。真珠帘卷玉楼空，天淡银河垂地。年年今夜，月华如练，长是人千里。\t愁肠已断无由醉，酒未到，先成泪。残灯明灭枕头欹，谙尽孤眠滋味。都来此事，眉间心上，无计相回避。", "topic": "秋天", "notes": ["香砌：有落花的台阶。", "寒声碎：寒风吹动落叶发出的轻微细碎的声音。", "真珠：珍珠。", "天淡：天空清澈无云。", "月华：月光。", "练：白色的丝绸。", "无由：无法。", "明灭：忽明忽暗。", "欹（qī）：倾斜，斜靠。", "谙（ān）尽：尝尽。", "都来：算来。"], "background": "此词具体的创作时间已无从考证，关于此词的创作意图，历来说法各异：唐圭璋认为此词是作者因久久客居他乡的愁苦触景生情而作。靳极苍认为此词是“思君之作”，“作者在外任时还念朝廷无人，君王无佐，忧心如焚，因此创作此词来抒发情感”。汪中认为此词是“为思念室家之作”。"}
]